Workbook

Sheet LEIA-ME
B1: Passo 3 da reconciliação: o que mudou no 2º semestre de 2024 e em dezembro?
B2: Planilha apartada. Lê os CSVs originais sem alterá-los. Base principal = assinaturas (01_Evidencias); ponto de partida = aba Tempo de 02_Triangulacao.
B4: PERGUNTAS
B5: 1. As assinaturas que entraram em 2024-S2 são de outro tipo (plano, cliente, canal…) ou o mesmo tipo de assinatura passou a cancelar mais? → aba Coorte_x_Fator
B6: 2. O que há de diferente em dezembro/2024? → aba Dezembro
B7: 3. Suporte e uso pioraram junto com o churn? → aba Sinais_no_tempo
B8: 4. O que diferencia as contas em que as 3 marcações concordam? → aba Subconjunto_limpo
B10: RESPOSTAS
B11: 1. Mesmo tipo de assinatura, cancelando mais. A taxa de encerramento em 30 dias sobe de ~0,7% para ~4,2% (cerca de 6x) em praticamente todas as categorias de plano, cobrança, trial, seats, indústria, país, canal e idade da conta. O mix muda um pouco em alguns fatores, mas, mantidas as taxas antigas, essa mudança explicaria quase nada do aumento (coluna O). É um efeito do período, não do mix.
B12: 2. Dezembro soma o efeito do período (muitas assinaturas novas encerrando em poucos dias) com uma concentração anormal de encerramentos em 29–31/12. Essa concentração precisa ser confirmada com a área (fechamento de ano, renovação, corte da extração) antes de ser lida como perda de cliente.
B13: 3. Não. Satisfação, tempo de resolução, primeira resposta, escalação, uso e erros ficam estáveis enquanto o churn sobe. Por isso "CS diz que a satisfação está ok" e "produto diz que o uso cresceu" não contradizem o churn: esses indicadores simplesmente não captam o que está mudando.
B14: 4. Contas limpas são parecidas em quase tudo. Mais assinaturas e mais uso no grupo churn é efeito mecânico; a concentração em DevTools vem do próprio churn_flag e não é confirmada por receita nem eventos.
... B21: • p-valores (Fisher exato, permutação) são calculados no script; contagens, % e médias são fórmulas sobre as abas Base_*.

Sheet Coorte_x_Fator
A1: O que mudou nas assinaturas iniciadas no 2º semestre de 2024?
A2: Só assinaturas com 30 dias observáveis (início até 01/12/2024). "% encerra em 30 dias" = assinaturas encerradas com até 30 dias de vida. Composição = peso de cada categoria dentro da coorte. Contagens e % são fórmulas; p-valores vêm do script (Fisher exato e permutação).
A4: Fator | B4: Categoria | C4: Até 2024-S1: assinaturas | D4: Até 2024-S1: encerram em 30 dias | E4: Até 2024-S1: % | F4: 2024-S2: assinaturas | G4: 2024-S2: encerram em 30 dias | H4: 2024-S2: % | I4: Aumento (S2 ÷ antes) | J4: p (Fisher) | K4: Composição até S1 | L4: Composição S2 | M4: Mudança de composição (p.p.) | N4: p da composição (fator) | O4: % S2 esperado só pela mudança de mix
A5: TODAS | C5: =COUNTIFS(Base_Assinaturas!$H$2:$H$5001,"Sim",Base_Assinaturas!$G$2:$G$5001,"Até 2024-S1") | D5: =SUMIFS(Base_Assinaturas!$I$2:$I$5001,Base_Assinaturas!$H$2:$H$5001,"Sim",Base_Assinaturas!$G$2:$G$5001,"Até 2024-S1") | E5: =D5/C5 | F5: =COUNTIFS(Base_Assinaturas!$H$2:$H$5001,"Sim",Base_Assinaturas!$G$2:$G$5001,"2024-S2") | G5: =SUMIFS(Base_Assinaturas!$I$2:$I$5001,Base_Assinaturas!$H$2:$H$5001,"Sim",Base_Assinaturas!$G$2:$G$5001,"2024-S2") | H5: =G5/F5 | I5: =IF(E5>0,H5/E5,"") | J5: 0 | O5: =E5
A6: Plano da assinatura | B6: Basic | C6: =COUNTIFS(Base_Assinaturas!$H$2:$H$5001,"Sim",Base_Assinaturas!$G$2:$G$5001,"Até 2024-S1",Base_Assinaturas!$M$2:$M$5001,"Basic") | D6: =SUMIFS(Base_Assinaturas!$I$2:$I$5001,Base_Assinaturas!$H$2:$H$5001,"Sim",Base_Assinaturas!$G$2:$G$5001,"Até 2024-S1",Base_Assinaturas!$M$2:$M$5001,"Basic") | E6: =IF(C6>0,D6/C6,"") | F6: =COUNTIFS(Base_Assinaturas!$H$2:$H$5001,"Sim",Base_Assinaturas!$G$2:$G$5001,"2024-S2",Base_Assinaturas!$M$2:$M$5001,"Basic") | G6: =SUMIFS(Base_Assinaturas!$I$2:$I$5001,Base_Assinaturas!$H$2:$H$5001,"Sim",Base_Assinaturas!$G$2:$G$5001,"2024-S2",Base_Assinaturas!$M$2:$M$5001,"Basic") | H6: =IF(F6>0,G6/F6,"") | I6: =IF(AND(ISNUMBER(E6),E6>0),H6/E6,"sem casos antes") | J6: 0 | K6: =C6/C$5 | L6: =F6/F$5 | M6: =(L6-K6)*100 | N6: 0.4346 | O6: =SUMPRODUCT(L6:L8,E6:E8)
B7: Enterprise | C7: =COUNTIFS(Base_Assinaturas!$H$2:$H$5001,"Sim",Base_Assinaturas!$G$2:$G$5001,"Até 2024-S1",Base_Assinaturas!$M$2:$M$5001,"Enterprise") | D7: =SUMIFS(Base_Assinaturas!$I$2:$I$5001,Base_Assinaturas!$H$2:$H$5001,"Sim",Base_Assinaturas!$G$2:$G$5001,"Até 2024-S1",Base_Assinaturas!$M$2:$M$5001,"Enterprise") | E7: =IF(C7>0,D7/C7,"") | F7: =COUNTIFS(Base_Assinaturas!$H$2:$H$5001,"Sim",Base_Assinaturas!$G$2:$G$5001,"2024-S2",Base_Assinaturas!$M$2:$M$5001,"Enterprise") | G7: =SUMIFS(Base_Assinaturas!$I$2:$I$5001,Base_Assinaturas!$H$2:$H$5001,"Sim",Base_Assinaturas!$G$2:$G$5001,"2024-S2",Base_Assinaturas!$M$2:$M$5001,"Enterprise") | H7: =IF(F7>0,G7/F7,"") | I7: =IF(AND(ISNUMBER(E7),E7>0),H7/E7,"sem casos antes") | J7: 0.000384 | K7: =C7/C$5 | L7: =F7/F$5 | M7: =(L7-K7)*100
B8: Pro | C8: =COUNTIFS(Base_Assinaturas!$H$2:$H$5001,"Sim",Base_Assinaturas!$G$2:$G$5001,"Até 2024-S1",Base_Assinaturas!$M$2:$M$5001,"Pro") | D8: =SUMIFS(Base_Assinaturas!$I$2:$I$5001,Base_Assinaturas!$H$2:$H$5001,"Sim",Base_Assinaturas!$G$2:$G$5001,"Até 2024-S1",Base_Assinaturas!$M$2:$M$5001,"Pro") | E8: =IF(C8>0,D8/C8,"") | F8: =COUNTIFS(Base_Assinaturas!$H$2:$H$5001,"Sim",Base_Assinaturas!$G$2:$G$5001,"2024-S2",Base_Assinaturas!$M$2:$M$5001,"Pro") | G8: =SUMIFS(Base_Assinaturas!$I$2:$I$5001,Base_Assinaturas!$H$2:$H$5001,"Sim",Base_Assinaturas!$G$2:$G$5001,"2024-S2",Base_Assinaturas!$M$2:$M$5001,"Pro") | H8: =IF(F8>0,G8/F8,"") | I8: =IF(AND(ISNUMBER(E8),E8>0),H8/E8,"sem casos antes") | J8: 0.0001 | K8: =C8/C$5 | L8: =F8/F$5 | M8: =(L8-K8)*100
A9: Cobrança | B9: annual | C9: =COUNTIFS(Base_Assinaturas!$H$2:$H$5001,"Sim",Base_Assinaturas!$G$2:$G$5001,"Até 2024-S1",Base_Assinaturas!$N$2:$N$5001,"annual") | D9: =SUMIFS(Base_Assinaturas!$I$2:$I$5001,Base_Assinaturas!$H$2:$H$5001,"Sim",Base_Assinaturas!$G$2:$G$5001,"Até 2024-S1",Base_Assinaturas!$N$2:$N$5001,"annual") | E9: =IF(C9>0,D9/C9,"") | F9: =COUNTIFS(Base_Assinaturas!$H$2:$H$5001,"Sim",Base_Assinaturas!$G$2:$G$5001,"2024-S2",Base_Assinaturas!$N$2:$N$5001,"annual") | G9: =SUMIFS(Base_Assinaturas!$I$2:$I$5001,Base_Assinaturas!$H$2:$H$5001,"Sim",Base_Assinaturas!$G$2:$G$5001,"2024-S2",Base_Assinaturas!$N$2:$N$5001,"annual") | H9: =IF(F9>0,G9/F9,"") | I9: =IF(AND(ISNUMBER(E9),E9>0),H9/E9,"sem casos antes") | J9: 0 | K9: =C9/C$5 | L9: =F9/F$5 | M9: =(L9-K9)*100 | N9: 0.7552 | O9: =SUMPRODUCT(L9:L10,E9:E10)
B10: monthly | C10: =COUNTIFS(Base_Assinaturas!$H$2:$H$5001,"Sim",Base_Assinaturas!$G$2:$G$5001,"Até 2024-S1",Base_Assinaturas!$N$2:$N$5001,"monthly") | D10: =SUMIFS(Base_Assinaturas!$I$2:$I$5001,Base_Assinaturas!$H$2:$H$5001,"Sim",Base_Assinaturas!$G$2:$G$5001,"Até 2024-S1",Base_Assinaturas!$N$2:$N$5001,"monthly") | E10: =IF(C10>0,D10/C10,"") | F10: =COUNTIFS(Base_Assinaturas!$H$2:$H$5001,"Sim",Base_Assinaturas!$G$2:$G$5001,"2024-S2",Base_Assinaturas!$N$2:$N$5001,"monthly") | G10: =SUMIFS(Base_Assinaturas!$I$2:$I$5001,Base_Assinaturas!$H$2:$H$5001,"Sim",Base_Assinaturas!$G$2:$G$5001,"2024-S2",Base_Assinaturas!$N$2:$N$5001,"monthly") | H10: =IF(F10>0,G10/F10,"") | I10: =IF(AND(ISNUMBER(E10),E10>0),H10/E10,"sem casos antes") | J10: 0 | K10: =C10/C$5 | L10: =F10/F$5 | M10: =(L10-K10)*100
A11: Trial | B11: Pago | C11: =COUNTIFS(Base_Assinaturas!$H$2:$H$5001,"Sim",Base_Assinaturas!$G$2:$G$5001,"Até 2024-S1",Base_Assinaturas!$O$2:$O$5001,"Pago") | D11: =SUMIFS(Base_Assinaturas!$I$2:$I$5001,Base_Assinaturas!$H$2:$H$5001,"Sim",Base_Assinaturas!$G$2:$G$5001,"Até 2024-S1",Base_Assinaturas!$O$2:$O$5001,"Pago") | E11: =IF(C11>0,D11/C11,"") | F11: =COUNTIFS(Base_Assinaturas!$H$2:$H$5001,"Sim",Base_Assinaturas!$G$2:$G$5001,"2024-S2",Base_Assinaturas!$O$2:$O$5001,"Pago") | G11: =SUMIFS(Base_Assinaturas!$I$2:$I$5001,Base_Assinaturas!$H$2:$H$5001,"Sim",Base_Assinaturas!$G$2:$G$5001,"2024-S2",Base_Assinaturas!$O$2:$O$5001,"Pago") | H11: =IF(F11>0,G11/F11,"") | I11: =IF(AND(ISNUMBER(E11),E11>0),H11/E11,"sem casos antes") | J11: 0 | K11: =C11/C$5 | L11: =F11/F$5 | M11: =(L11-K11)*100 | N11: 0.3736 | O11: =SUMPRODUCT(L11:L12,E11:E12)
B12: Trial | C12: =COUNTIFS(Base_Assinaturas!$H$2:$H$5001,"Sim",Base_Assinaturas!$G$2:$G$5001,"Até 2024-S1",Base_Assinaturas!$O$2:$O$5001,"Trial") | D12: =SUMIFS(Base_Assinaturas!$I$2:$I$5001,Base_Assinaturas!$H$2:$H$5001,"Sim",Base_Assinaturas!$G$2:$G$5001,"Até 2024-S1",Base_Assinaturas!$O$2:$O$5001,"Trial") | E12: =IF(C12>0,D12/C12,"") | F12: =COUNTIFS(Base_Assinaturas!$H$2:$H$5001,"Sim",Base_Assinaturas!$G$2:$G$5001,"2024-S2",Base_Assinaturas!$O$2:$O$5001,"Trial") | G12: =SUMIFS(Base_Assinaturas!$I$2:$I$5001,Base_Assinaturas!$H$2:$H$5001,"Sim",Base_Assinaturas!$G$2:$G$5001,"2024-S2",Base_Assinaturas!$O$2:$O$5001,"Trial") | H12: =IF(F12>0,G12/F12,"") | I12: =IF(AND(ISNUMBER(E12),E12>0),H12/E12,"sem casos antes") | J12: 0.001212 | K12: =C12/C$5 | L12: =F12/F$5 | M12: =(L12-K12)*100
A13: Renovação automática | B13: Não | C13: =COUNTIFS(Base_Assinaturas!$H$2:$H$5001,"Sim",Base_Assinaturas!$G$2:$G$5001,"Até 2024-S1",Base_Assinaturas!$P$2:$P$5001,"Não") | D13: =SUMIFS(Base_Assinaturas!$I$2:$I$5001,Base_Assinaturas!$H$2:$H$5001,"Sim",Base_Assinaturas!$G$2:$G$5001,"Até 2024-S1",Base_Assinaturas!$P$2:$P$5001,"Não") | E13: =IF(C13>0,D13/C13,"") | F13: =COUNTIFS(Base_Assinaturas!$H$2:$H$5001,"Sim",Base_Assinaturas!$G$2:$G$5001,"2024-S2",Base_Assinaturas!$P$2:$P$5001,"Não") | G13: =SUMIFS(Base_Assinaturas!$I$2:$I$5001,Base_Assinaturas!$H$2:$H$5001,"Sim",Base_Assinaturas!$G$2:$G$5001,"2024-S2",Base_Assinaturas!$P$2:$P$5001,"Não") | H13: =IF(F13>0,G13/F13,"") | I13: =IF(AND(ISNUMBER(E13),E13>0),H13/E13,"sem casos antes") | J13: 0.00016 | K13: =C13/C$5 | L13: =F13/F$5 | M13: =(L13-K13)*100 | N13: 0.3926 | O13: =SUMPRODUCT(L13:L14,E13:E14)
B14: Sim | C14: =COUNTIFS(Base_Assinaturas!$H$2:$H$5001,"Sim",Base_Assinaturas!$G$2:$G$5001,"Até 2024-S1",Base_Assinaturas!$P$2:$P$5001,"Sim") | D14: =SUMIFS(Base_Assinaturas!$I$2:$I$5001,Base_Assinaturas!$H$2:$H$5001,"Sim",Base_Assinaturas!$G$2:$G$5001,"Até 2024-S1",Base_Assinaturas!$P$2:$P$5001,"Sim") | E14: =IF(C14>0,D14/C14,"") | F14: =COUNTIFS(Base_Assinaturas!$H$2:$H$5001,"Sim",Base_Assinaturas!$G$2:$G$5001,"2024-S2",Base_Assinaturas!$P$2:$P$5001,"Sim") | G14: =SUMIFS(Base_Assinaturas!$I$2:$I$5001,Base_Assinaturas!$H$2:$H$5001,"Sim",Base_Assinaturas!$G$2:$G$5001,"2024-S2",Base_Assinaturas!$P$2:$P$5001,"Sim") | H14: =IF(F14>0,G14/F14,"") | I14: =IF(AND(ISNUMBER(E14),E14>0),H14/E14,"sem casos antes") | J14: 0 | K14: =C14/C$5 | L14: =F14/F$5 | M14: =(L14-K14)*100
A15: Upgrade na assinatura | B15: Não | C15: =COUNTIFS(Base_Assinaturas!$H$2:$H$5001,"Sim",Base_Assinaturas!$G$2:$G$5001,"Até 2024-S1",Base_Assinaturas!$Q$2:$Q$5001,"Não") | D15: =SUMIFS(Base_Assinaturas!$I$2:$I$5001,Base_Assinaturas!$H$2:$H$5001,"Sim",Base_Assinaturas!$G$2:$G$5001,"Até 2024-S1",Base_Assinaturas!$Q$2:$Q$5001,"Não") | E15: =IF(C15>0,D15/C15,"") | F15: =COUNTIFS(Base_Assinaturas!$H$2:$H$5001,"Sim",Base_Assinaturas!$G$2:$G$5001,"2024-S2",Base_Assinaturas!$Q$2:$Q$5001,"Não") | G15: =SUMIFS(Base_Assinaturas!$I$2:$I$5001,Base_Assinaturas!$H$2:$H$5001,"Sim",Base_Assinaturas!$G$2:$G$5001,"2024-S2",Base_Assinaturas!$Q$2:$Q$5001,"Não") | H15: =IF(F15>0,G15/F15,"") | I15: =IF(AND(ISNUMBER(E15),E15>0),H15/E15,"sem casos antes") | J15: 0 | K15: =C15/C$5 | L15: =F15/F$5 | M15: =(L15-K15)*100 | N15: 0.1089 | O15: =SUMPRODUCT(L15:L16,E15:E16)
B16: Sim | C16: =COUNTIFS(Base_Assinaturas!$H$2:$H$5001,"Sim",Base_Assinaturas!$G$2:$G$5001,"Até 2024-S1",Base_Assinaturas!$Q$2:$Q$5001,"Sim") | D16: =SUMIFS(Base_Assinaturas!$I$2:$I$5001,Base_Assinaturas!$H$2:$H$5001,"Sim",Base_Assinaturas!$G$2:$G$5001,"Até 2024-S1",Base_Assinaturas!$Q$2:$Q$5001,"Sim") | E16: =IF(C16>0,D16/C16,"") | F16: =COUNTIFS(Base_Assinaturas!$H$2:$H$5001,"Sim",Base_Assinaturas!$G$2:$G$5001,"2024-S2",Base_Assinaturas!$Q$2:$Q$5001,"Sim") | G16: =SUMIFS(Base_Assinaturas!$I$2:$I$5001,Base_Assinaturas!$H$2:$H$5001,"Sim",Base_Assinaturas!$G$2:$G$5001,"2024-S2",Base_Assinaturas!$Q$2:$Q$5001,"Sim") | H16: =IF(F16>0,G16/F16,"") | I16: =IF(AND(ISNUMBER(E16),E16>0),H16/E16,"sem casos antes") | J16: 0.089953 | K16: =C16/C$5 | L16: =F16/F$5 | M16: =(L16-K16)*100
A17: Downgrade na assinatura | B17: Não | C17: =COUNTIFS(Base_Assinaturas!$H$2:$H$5001,"Sim",Base_Assinaturas!$G$2:$G$5001,"Até 2024-S1",Base_Assinaturas!$R$2:$R$5001,"Não") | D17: =SUMIFS(Base_Assinaturas!$I$2:$I$5001,Base_Assinaturas!$H$2:$H$5001,"Sim",Base_Assinaturas!$G$2:$G$5001,"Até 2024-S1",Base_Assinaturas!$R$2:$R$5001,"Não") | E17: =IF(C17>0,D17/C17,"") | F17: =COUNTIFS(Base_Assinaturas!$H$2:$H$5001,"Sim",Base_Assinaturas!$G$2:$G$5001,"2024-S2",Base_Assinaturas!$R$2:$R$5001,"Não") | G17: =SUMIFS(Base_Assinaturas!$I$2:$I$5001,Base_Assinaturas!$H$2:$H$5001,"Sim",Base_Assinaturas!$G$2:$G$5001,"2024-S2",Base_Assinaturas!$R$2:$R$5001,"Não") | H17: =IF(F17>0,G17/F17,"") | I17: =IF(AND(ISNUMBER(E17),E17>0),H17/E17,"sem casos antes") | J17: 0 | K17: =C17/C$5 | L17: =F17/F$5 | M17: =(L17-K17)*100 | N17: 0.8342 | O17: =SUMPRODUCT(L17:L18,E17:E18)
B18: Sim | C18: =COUNTIFS(Base_Assinaturas!$H$2:$H$5001,"Sim",Base_Assinaturas!$G$2:$G$5001,"Até 2024-S1",Base_Assinaturas!$R$2:$R$5001,"Sim") | D18: =SUMIFS(Base_Assinaturas!$I$2:$I$5001,Base_Assinaturas!$H$2:$H$5001,"Sim",Base_Assinaturas!$G$2:$G$5001,"Até 2024-S1",Base_Assinaturas!$R$2:$R$5001,"Sim") | E18: =IF(C18>0,D18/C18,"") | F18: =COUNTIFS(Base_Assinaturas!$H$2:$H$5001,"Sim",Base_Assinaturas!$G$2:$G$5001,"2024-S2",Base_Assinaturas!$R$2:$R$5001,"Sim") | G18: =SUMIFS(Base_Assinaturas!$I$2:$I$5001,Base_Assinaturas!$H$2:$H$5001,"Sim",Base_Assinaturas!$G$2:$G$5001,"2024-S2",Base_Assinaturas!$R$2:$R$5001,"Sim") | H18: =IF(F18>0,G18/F18,"") | I18: =IF(AND(ISNUMBER(E18),E18>0),H18/E18,"sem casos antes") | J18: 0.231124 | K18: =C18/C$5 | L18: =F18/F$5 | M18: =(L18-K18)*100
A19: Seats da assinatura | B19: 16–40 | C19: =COUNTIFS(Base_Assinaturas!$H$2:$H$5001,"Sim",Base_Assinaturas!$G$2:$G$5001,"Até 2024-S1",Base_Assinaturas!$S$2:$S$5001,"16–40") | D19: =SUMIFS(Base_Assinaturas!$I$2:$I$5001,Base_Assinaturas!$H$2:$H$5001,"Sim",Base_Assinaturas!$G$2:$G$5001,"Até 2024-S1",Base_Assinaturas!$S$2:$S$5001,"16–40") | E19: =IF(C19>0,D19/C19,"") | F19: =COUNTIFS(Base_Assinaturas!$H$2:$H$5001,"Sim",Base_Assinaturas!$G$2:$G$5001,"2024-S2",Base_Assinaturas!$S$2:$S$5001,"16–40") | G19: =SUMIFS(Base_Assinaturas!$I$2:$I$5001,Base_Assinaturas!$H$2:$H$5001,"Sim",Base_Assinaturas!$G$2:$G$5001,"2024-S2",Base_Assinaturas!$S$2:$S$5001,"16–40") | H19: =IF(F19>0,G19/F19,"") | I19: =IF(AND(ISNUMBER(E19),E19>0),H19/E19,"sem casos antes") | J19: 2e-06 | K19: =C19/C$5 | L19: =F19/F$5 | M19: =(L19-K19)*100 | N19: 0.7552 | O19: =SUMPRODUCT(L19:L22,E19:E22)
B20: 1–5 | C20: =COUNTIFS(Base_Assinaturas!$H$2:$H$5001,"Sim",Base_Assinaturas!$G$2:$G$5001,"Até 2024-S1",Base_Assinaturas!$S$2:$S$5001,"1–5") | D20: =SUMIFS(Base_Assinaturas!$I$2:$I$5001,Base_Assinaturas!$H$2:$H$5001,"Sim",Base_Assinaturas!$G$2:$G$5001,"Até 2024-S1",Base_Assinaturas!$S$2:$S$5001,"1–5") | E20: =IF(C20>0,D20/C20,"") | F20: =COUNTIFS(Base_Assinaturas!$H$2:$H$5001,"Sim",Base_Assinaturas!$G$2:$G$5001,"2024-S2",Base_Assinaturas!$S$2:$S$5001,"1–5") | G20: =SUMIFS(Base_Assinaturas!$I$2:$I$5001,Base_Assinaturas!$H$2:$H$5001,"Sim",Base_Assinaturas!$G$2:$G$5001,"2024-S2",Base_Assinaturas!$S$2:$S$5001,"1–5") | H20: =IF(F20>0,G20/F20,"") | I20: =IF(AND(ISNUMBER(E20),E20>0),H20/E20,"sem casos antes") | J20: 0.013717 | K20: =C20/C$5 | L20: =F20/F$5 | M20: =(L20-K20)*100
B21: 41+ | C21: =COUNTIFS(Base_Assinaturas!$H$2:$H$5001,"Sim",Base_Assinaturas!$G$2:$G$5001,"Até 2024-S1",Base_Assinaturas!$S$2:$S$5001,"41+") | D21: =SUMIFS(Base_Assinaturas!$I$2:$I$5001,Base_Assinaturas!$H$2:$H$5001,"Sim",Base_Assinaturas!$G$2:$G$5001,"Até 2024-S1",Base_Assinaturas!$S$2:$S$5001,"41+") | E21: =IF(C21>0,D21/C21,"") | F21: =COUNTIFS(Base_Assinaturas!$H$2:$H$5001,"Sim",Base_Assinaturas!$G$2:$G$5001,"2024-S2",Base_Assinaturas!$S$2:$S$5001,"41+") | G21: =SUMIFS(Base_Assinaturas!$I$2:$I$5001,Base_Assinaturas!$H$2:$H$5001,"Sim",Base_Assinaturas!$G$2:$G$5001,"2024-S2",Base_Assinaturas!$S$2:$S$5001,"41+") | H21: =IF(F21>0,G21/F21,"") | I21: =IF(AND(ISNUMBER(E21),E21>0),H21/E21,"sem casos antes") | J21: 6.8e-05 | K21: =C21/C$5 | L21: =F21/F$5 | M21: =(L21-K21)*100
B22: 6–15 | C22: =COUNTIFS(Base_Assinaturas!$H$2:$H$5001,"Sim",Base_Assinaturas!$G$2:$G$5001,"Até 2024-S1",Base_Assinaturas!$S$2:$S$5001,"6–15") | D22: =SUMIFS(Base_Assinaturas!$I$2:$I$5001,Base_Assinaturas!$H$2:$H$5001,"Sim",Base_Assinaturas!$G$2:$G$5001,"Até 2024-S1",Base_Assinaturas!$S$2:$S$5001,"6–15") | E22: =IF(C22>0,D22/C22,"") | F22: =COUNTIFS(Base_Assinaturas!$H$2:$H$5001,"Sim",Base_Assinaturas!$G$2:$G$5001,"2024-S2",Base_Assinaturas!$S$2:$S$5001,"6–15") | G22: =SUMIFS(Base_Assinaturas!$I$2:$I$5001,Base_Assinaturas!$H$2:$H$5001,"Sim",Base_Assinaturas!$G$2:$G$5001,"2024-S2",Base_Assinaturas!$S$2:$S$5001,"6–15") | H22: =IF(F22>0,G22/F22,"") | I22: =IF(AND(ISNUMBER(E22),E22>0),H22/E22,"sem casos antes") | J22: 0.009253 | K22: =C22/C$5 | L22: =F22/F$5 | M22: =(L22-K22)*100
A23: Idade da conta ao assinar | B23: 181–365 dias | C23: =COUNTIFS(Base_Assinaturas!$H$2:$H$5001,"Sim",Base_Assinaturas!$G$2:$G$5001,"Até 2024-S1",Base_Assinaturas!$T$2:$T$5001,"181–365 dias") | D23: =SUMIFS(Base_Assinaturas!$I$2:$I$5001,Base_Assinaturas!$H$2:$H$5001,"Sim",Base_Assinaturas!$G$2:$G$5001,"Até 2024-S1",Base_Assinaturas!$T$2:$T$5001,"181–365 dias") | E23: =IF(C23>0,D23/C23,"") | F23: =COUNTIFS(Base_Assinaturas!$H$2:$H$5001,"Sim",Base_Assinaturas!$G$2:$G$5001,"2024-S2",Base_Assinaturas!$T$2:$T$5001,"181–365 dias") | G23: =SUMIFS(Base_Assinaturas!$I$2:$I$5001,Base_Assinaturas!$H$2:$H$5001,"Sim",Base_Assinaturas!$G$2:$G$5001,"2024-S2",Base_Assinaturas!$T$2:$T$5001,"181–365 dias") | H23: =IF(F23>0,G23/F23,"") | I23: =IF(AND(ISNUMBER(E23),E23>0),H23/E23,"sem casos antes") | J23: 0.025388 | K23: =C23/C$5 | L23: =F23/F$5 | M23: =(L23-K23)*100 | N23: 0.001 | O23: =SUMPRODUCT(L23:L27,E23:E27)
B24: 31–90 dias | C24: =COUNTIFS(Base_Assinaturas!$H$2:$H$5001,"Sim",Base_Assinaturas!$G$2:$G$5001,"Até 2024-S1",Base_Assinaturas!$T$2:$T$5001,"31–90 dias") | D24: =SUMIFS(Base_Assinaturas!$I$2:$I$5001,Base_Assinaturas!$H$2:$H$5001,"Sim",Base_Assinaturas!$G$2:$G$5001,"Até 2024-S1",Base_Assinaturas!$T$2:$T$5001,"31–90 dias") | E24: =IF(C24>0,D24/C24,"") | F24: =COUNTIFS(Base_Assinaturas!$H$2:$H$5001,"Sim",Base_Assinaturas!$G$2:$G$5001,"2024-S2",Base_Assinaturas!$T$2:$T$5001,"31–90 dias") | G24: =SUMIFS(Base_Assinaturas!$I$2:$I$5001,Base_Assinaturas!$H$2:$H$5001,"Sim",Base_Assinaturas!$G$2:$G$5001,"2024-S2",Base_Assinaturas!$T$2:$T$5001,"31–90 dias") | H24: =IF(F24>0,G24/F24,"") | I24: =IF(AND(ISNUMBER(E24),E24>0),H24/E24,"sem casos antes") | J24: 0.000833 | K24: =C24/C$5 | L24: =F24/F$5 | M24: =(L24-K24)*100
B25: 91–180 dias | C25: =COUNTIFS(Base_Assinaturas!$H$2:$H$5001,"Sim",Base_Assinaturas!$G$2:$G$5001,"Até 2024-S1",Base_Assinaturas!$T$2:$T$5001,"91–180 dias") | D25: =SUMIFS(Base_Assinaturas!$I$2:$I$5001,Base_Assinaturas!$H$2:$H$5001,"Sim",Base_Assinaturas!$G$2:$G$5001,"Até 2024-S1",Base_Assinaturas!$T$2:$T$5001,"91–180 dias") | E25: =IF(C25>0,D25/C25,"") | F25: =COUNTIFS(Base_Assinaturas!$H$2:$H$5001,"Sim",Base_Assinaturas!$G$2:$G$5001,"2024-S2",Base_Assinaturas!$T$2:$T$5001,"91–180 dias") | G25: =SUMIFS(Base_Assinaturas!$I$2:$I$5001,Base_Assinaturas!$H$2:$H$5001,"Sim",Base_Assinaturas!$G$2:$G$5001,"2024-S2",Base_Assinaturas!$T$2:$T$5001,"91–180 dias") | H25: =IF(F25>0,G25/F25,"") | I25: =IF(AND(ISNUMBER(E25),E25>0),H25/E25,"sem casos antes") | J25: 1.1e-05 | K25: =C25/C$5 | L25: =F25/F$5 | M25: =(L25-K25)*100
B26: Conta nova (≤ 30 dias) | C26: =COUNTIFS(Base_Assinaturas!$H$2:$H$5001,"Sim",Base_Assinaturas!$G$2:$G$5001,"Até 2024-S1",Base_Assinaturas!$T$2:$T$5001,"Conta nova (≤ 30 dias)") | D26: =SUMIFS(Base_Assinaturas!$I$2:$I$5001,Base_Assinaturas!$H$2:$H$5001,"Sim",Base_Assinaturas!$G$2:$G$5001,"Até 2024-S1",Base_Assinaturas!$T$2:$T$5001,"Conta nova (≤ 30 dias)") | E26: =IF(C26>0,D26/C26,"") | F26: =COUNTIFS(Base_Assinaturas!$H$2:$H$5001,"Sim",Base_Assinaturas!$G$2:$G$5001,"2024-S2",Base_Assinaturas!$T$2:$T$5001,"Conta nova (≤ 30 dias)") | G26: =SUMIFS(Base_Assinaturas!$I$2:$I$5001,Base_Assinaturas!$H$2:$H$5001,"Sim",Base_Assinaturas!$G$2:$G$5001,"2024-S2",Base_Assinaturas!$T$2:$T$5001,"Conta nova (≤ 30 dias)") | H26: =IF(F26>0,G26/F26,"") | I26: =IF(AND(ISNUMBER(E26),E26>0),H26/E26,"sem casos antes") | J26: 0.000529 | K26: =C26/C$5 | L26: =F26/F$5 | M26: =(L26-K26)*100
B27: Mais de 365 dias | C27: =COUNTIFS(Base_Assinaturas!$H$2:$H$5001,"Sim",Base_Assinaturas!$G$2:$G$5001,"Até 2024-S1",Base_Assinaturas!$T$2:$T$5001,"Mais de 365 dias") | D27: =SUMIFS(Base_Assinaturas!$I$2:$I$5001,Base_Assinaturas!$H$2:$H$5001,"Sim",Base_Assinaturas!$G$2:$G$5001,"Até 2024-S1",Base_Assinaturas!$T$2:$T$5001,"Mais de 365 dias") | E27: =IF(C27>0,D27/C27,"") | F27: =COUNTIFS(Base_Assinaturas!$H$2:$H$5001,"Sim",Base_Assinaturas!$G$2:$G$5001,"2024-S2",Base_Assinaturas!$T$2:$T$5001,"Mais de 365 dias") | G27: =SUMIFS(Base_Assinaturas!$I$2:$I$5001,Base_Assinaturas!$H$2:$H$5001,"Sim",Base_Assinaturas!$G$2:$G$5001,"2024-S2",Base_Assinaturas!$T$2:$T$5001,"Mais de 365 dias") | H27: =IF(F27>0,G27/F27,"") | I27: =IF(AND(ISNUMBER(E27),E27>0),H27/E27,"sem casos antes") | J27: 0.054163 | K27: =C27/C$5 | L27: =F27/F$5 | M27: =(L27-K27)*100
A28: Indústria | B28: Cybersecurity | C28: =COUNTIFS(Base_Assinaturas!$H$2:$H$5001,"Sim",Base_Assinaturas!$G$2:$G$5001,"Até 2024-S1",Base_Assinaturas!$U$2:$U$5001,"Cybersecurity") | D28: =SUMIFS(Base_Assinaturas!$I$2:$I$5001,Base_Assinaturas!$H$2:$H$5001,"Sim",Base_Assinaturas!$G$2:$G$5001,"Até 2024-S1",Base_Assinaturas!$U$2:$U$5001,"Cybersecurity") | E28: =IF(C28>0,D28/C28,"") | F28: =COUNTIFS(Base_Assinaturas!$H$2:$H$5001,"Sim",Base_Assinaturas!$G$2:$G$5001,"2024-S2",Base_Assinaturas!$U$2:$U$5001,"Cybersecurity") | G28: =SUMIFS(Base_Assinaturas!$I$2:$I$5001,Base_Assinaturas!$H$2:$H$5001,"Sim",Base_Assinaturas!$G$2:$G$5001,"2024-S2",Base_Assinaturas!$U$2:$U$5001,"Cybersecurity") | H28: =IF(F28>0,G28/F28,"") | I28: =IF(AND(ISNUMBER(E28),E28>0),H28/E28,"sem casos antes") | J28: 0.000915 | K28: =C28/C$5 | L28: =F28/F$5 | M28: =(L28-K28)*100 | N28: 0.001 | O28: =SUMPRODUCT(L28:L32,E28:E32)
B29: DevTools | C29: =COUNTIFS(Base_Assinaturas!$H$2:$H$5001,"Sim",Base_Assinaturas!$G$2:$G$5001,"Até 2024-S1",Base_Assinaturas!$U$2:$U$5001,"DevTools") | D29: =SUMIFS(Base_Assinaturas!$I$2:$I$5001,Base_Assinaturas!$H$2:$H$5001,"Sim",Base_Assinaturas!$G$2:$G$5001,"Até 2024-S1",Base_Assinaturas!$U$2:$U$5001,"DevTools") | E29: =IF(C29>0,D29/C29,"") | F29: =COUNTIFS(Base_Assinaturas!$H$2:$H$5001,"Sim",Base_Assinaturas!$G$2:$G$5001,"2024-S2",Base_Assinaturas!$U$2:$U$5001,"DevTools") | G29: =SUMIFS(Base_Assinaturas!$I$2:$I$5001,Base_Assinaturas!$H$2:$H$5001,"Sim",Base_Assinaturas!$G$2:$G$5001,"2024-S2",Base_Assinaturas!$U$2:$U$5001,"DevTools") | H29: =IF(F29>0,G29/F29,"") | I29: =IF(AND(ISNUMBER(E29),E29>0),H29/E29,"sem casos antes") | J29: 0.001714 | K29: =C29/C$5 | L29: =F29/F$5 | M29: =(L29-K29)*100
B30: EdTech | C30: =COUNTIFS(Base_Assinaturas!$H$2:$H$5001,"Sim",Base_Assinaturas!$G$2:$G$5001,"Até 2024-S1",Base_Assinaturas!$U$2:$U$5001,"EdTech") | D30: =SUMIFS(Base_Assinaturas!$I$2:$I$5001,Base_Assinaturas!$H$2:$H$5001,"Sim",Base_Assinaturas!$G$2:$G$5001,"Até 2024-S1",Base_Assinaturas!$U$2:$U$5001,"EdTech") | E30: =IF(C30>0,D30/C30,"") | F30: =COUNTIFS(Base_Assinaturas!$H$2:$H$5001,"Sim",Base_Assinaturas!$G$2:$G$5001,"2024-S2",Base_Assinaturas!$U$2:$U$5001,"EdTech") | G30: =SUMIFS(Base_Assinaturas!$I$2:$I$5001,Base_Assinaturas!$H$2:$H$5001,"Sim",Base_Assinaturas!$G$2:$G$5001,"2024-S2",Base_Assinaturas!$U$2:$U$5001,"EdTech") | H30: =IF(F30>0,G30/F30,"") | I30: =IF(AND(ISNUMBER(E30),E30>0),H30/E30,"sem casos antes") | J30: 0.120218 | K30: =C30/C$5 | L30: =F30/F$5 | M30: =(L30-K30)*100
B31: FinTech | C31: =COUNTIFS(Base_Assinaturas!$H$2:$H$5001,"Sim",Base_Assinaturas!$G$2:$G$5001,"Até 2024-S1",Base_Assinaturas!$U$2:$U$5001,"FinTech") | D31: =SUMIFS(Base_Assinaturas!$I$2:$I$5001,Base_Assinaturas!$H$2:$H$5001,"Sim",Base_Assinaturas!$G$2:$G$5001,"Até 2024-S1",Base_Assinaturas!$U$2:$U$5001,"FinTech") | E31: =IF(C31>0,D31/C31,"") | F31: =COUNTIFS(Base_Assinaturas!$H$2:$H$5001,"Sim",Base_Assinaturas!$G$2:$G$5001,"2024-S2",Base_Assinaturas!$U$2:$U$5001,"FinTech") | G31: =SUMIFS(Base_Assinaturas!$I$2:$I$5001,Base_Assinaturas!$H$2:$H$5001,"Sim",Base_Assinaturas!$G$2:$G$5001,"2024-S2",Base_Assinaturas!$U$2:$U$5001,"FinTech") | H31: =IF(F31>0,G31/F31,"") | I31: =IF(AND(ISNUMBER(E31),E31>0),H31/E31,"sem casos antes") | J31: 6.4e-05 | K31: =C31/C$5 | L31: =F31/F$5 | M31: =(L31-K31)*100
B32: HealthTech | C32: =COUNTIFS(Base_Assinaturas!$H$2:$H$5001,"Sim",Base_Assinaturas!$G$2:$G$5001,"Até 2024-S1",Base_Assinaturas!$U$2:$U$5001,"HealthTech") | D32: =SUMIFS(Base_Assinaturas!$I$2:$I$5001,Base_Assinaturas!$H$2:$H$5001,"Sim",Base_Assinaturas!$G$2:$G$5001,"Até 2024-S1",Base_Assinaturas!$U$2:$U$5001,"HealthTech") | E32: =IF(C32>0,D32/C32,"") | F32: =COUNTIFS(Base_Assinaturas!$H$2:$H$5001,"Sim",Base_Assinaturas!$G$2:$G$5001,"2024-S2",Base_Assinaturas!$U$2:$U$5001,"HealthTech") | G32: =SUMIFS(Base_Assinaturas!$I$2:$I$5001,Base_Assinaturas!$H$2:$H$5001,"Sim",Base_Assinaturas!$G$2:$G$5001,"2024-S2",Base_Assinaturas!$U$2:$U$5001,"HealthTech") | H32: =IF(F32>0,G32/F32,"") | I32: =IF(AND(ISNUMBER(E32),E32>0),H32/E32,"sem casos antes") | J32: 0.000589 | K32: =C32/C$5 | L32: =F32/F$5 | M32: =(L32-K32)*100
A33: País | B33: AU | C33: =COUNTIFS(Base_Assinaturas!$H$2:$H$5001,"Sim",Base_Assinaturas!$G$2:$G$5001,"Até 2024-S1",Base_Assinaturas!$V$2:$V$5001,"AU") | D33: =SUMIFS(Base_Assinaturas!$I$2:$I$5001,Base_Assinaturas!$H$2:$H$5001,"Sim",Base_Assinaturas!$G$2:$G$5001,"Até 2024-S1",Base_Assinaturas!$V$2:$V$5001,"AU") | E33: =IF(C33>0,D33/C33,"") | F33: =COUNTIFS(Base_Assinaturas!$H$2:$H$5001,"Sim",Base_Assinaturas!$G$2:$G$5001,"2024-S2",Base_Assinaturas!$V$2:$V$5001,"AU") | G33: =SUMIFS(Base_Assinaturas!$I$2:$I$5001,Base_Assinaturas!$H$2:$H$5001,"Sim",Base_Assinaturas!$G$2:$G$5001,"2024-S2",Base_Assinaturas!$V$2:$V$5001,"AU") | H33: =IF(F33>0,G33/F33,"") | I33: =IF(AND(ISNUMBER(E33),E33>0),H33/E33,"sem casos antes") | J33: 0.340355 | K33: =C33/C$5 | L33: =F33/F$5 | M33: =(L33-K33)*100 | N33: 0.022 | O33: =SUMPRODUCT(L33:L39,E33:E39)
B34: CA | C34: =COUNTIFS(Base_Assinaturas!$H$2:$H$5001,"Sim",Base_Assinaturas!$G$2:$G$5001,"Até 2024-S1",Base_Assinaturas!$V$2:$V$5001,"CA") | D34: =SUMIFS(Base_Assinaturas!$I$2:$I$5001,Base_Assinaturas!$H$2:$H$5001,"Sim",Base_Assinaturas!$G$2:$G$5001,"Até 2024-S1",Base_Assinaturas!$V$2:$V$5001,"CA") | E34: =IF(C34>0,D34/C34,"") | F34: =COUNTIFS(Base_Assinaturas!$H$2:$H$5001,"Sim",Base_Assinaturas!$G$2:$G$5001,"2024-S2",Base_Assinaturas!$V$2:$V$5001,"CA") | G34: =SUMIFS(Base_Assinaturas!$I$2:$I$5001,Base_Assinaturas!$H$2:$H$5001,"Sim",Base_Assinaturas!$G$2:$G$5001,"2024-S2",Base_Assinaturas!$V$2:$V$5001,"CA") | H34: =IF(F34>0,G34/F34,"") | I34: =IF(AND(ISNUMBER(E34),E34>0),H34/E34,"sem casos antes") | J34: 0.042743 | K34: =C34/C$5 | L34: =F34/F$5 | M34: =(L34-K34)*100
B35: DE | C35: =COUNTIFS(Base_Assinaturas!$H$2:$H$5001,"Sim",Base_Assinaturas!$G$2:$G$5001,"Até 2024-S1",Base_Assinaturas!$V$2:$V$5001,"DE") | D35: =SUMIFS(Base_Assinaturas!$I$2:$I$5001,Base_Assinaturas!$H$2:$H$5001,"Sim",Base_Assinaturas!$G$2:$G$5001,"Até 2024-S1",Base_Assinaturas!$V$2:$V$5001,"DE") | E35: =IF(C35>0,D35/C35,"") | F35: =COUNTIFS(Base_Assinaturas!$H$2:$H$5001,"Sim",Base_Assinaturas!$G$2:$G$5001,"2024-S2",Base_Assinaturas!$V$2:$V$5001,"DE") | G35: =SUMIFS(Base_Assinaturas!$I$2:$I$5001,Base_Assinaturas!$H$2:$H$5001,"Sim",Base_Assinaturas!$G$2:$G$5001,"2024-S2",Base_Assinaturas!$V$2:$V$5001,"DE") | H35: =IF(F35>0,G35/F35,"") | I35: =IF(AND(ISNUMBER(E35),E35>0),H35/E35,"sem casos antes") | J35: 0.571033 | K35: =C35/C$5 | L35: =F35/F$5 | M35: =(L35-K35)*100
B36: FR | C36: =COUNTIFS(Base_Assinaturas!$H$2:$H$5001,"Sim",Base_Assinaturas!$G$2:$G$5001,"Até 2024-S1",Base_Assinaturas!$V$2:$V$5001,"FR") | D36: =SUMIFS(Base_Assinaturas!$I$2:$I$5001,Base_Assinaturas!$H$2:$H$5001,"Sim",Base_Assinaturas!$G$2:$G$5001,"Até 2024-S1",Base_Assinaturas!$V$2:$V$5001,"FR") | E36: =IF(C36>0,D36/C36,"") | F36: =COUNTIFS(Base_Assinaturas!$H$2:$H$5001,"Sim",Base_Assinaturas!$G$2:$G$5001,"2024-S2",Base_Assinaturas!$V$2:$V$5001,"FR") | G36: =SUMIFS(Base_Assinaturas!$I$2:$I$5001,Base_Assinaturas!$H$2:$H$5001,"Sim",Base_Assinaturas!$G$2:$G$5001,"2024-S2",Base_Assinaturas!$V$2:$V$5001,"FR") | H36: =IF(F36>0,G36/F36,"") | I36: =IF(AND(ISNUMBER(E36),E36>0),H36/E36,"sem casos antes") | J36: 0.13173 | K36: =C36/C$5 | L36: =F36/F$5 | M36: =(L36-K36)*100
B37: IN | C37: =COUNTIFS(Base_Assinaturas!$H$2:$H$5001,"Sim",Base_Assinaturas!$G$2:$G$5001,"Até 2024-S1",Base_Assinaturas!$V$2:$V$5001,"IN") | D37: =SUMIFS(Base_Assinaturas!$I$2:$I$5001,Base_Assinaturas!$H$2:$H$5001,"Sim",Base_Assinaturas!$G$2:$G$5001,"Até 2024-S1",Base_Assinaturas!$V$2:$V$5001,"IN") | E37: =IF(C37>0,D37/C37,"") | F37: =COUNTIFS(Base_Assinaturas!$H$2:$H$5001,"Sim",Base_Assinaturas!$G$2:$G$5001,"2024-S2",Base_Assinaturas!$V$2:$V$5001,"IN") | G37: =SUMIFS(Base_Assinaturas!$I$2:$I$5001,Base_Assinaturas!$H$2:$H$5001,"Sim",Base_Assinaturas!$G$2:$G$5001,"2024-S2",Base_Assinaturas!$V$2:$V$5001,"IN") | H37: =IF(F37>0,G37/F37,"") | I37: =IF(AND(ISNUMBER(E37),E37>0),H37/E37,"sem casos antes") | J37: 0.000986 | K37: =C37/C$5 | L37: =F37/F$5 | M37: =(L37-K37)*100
B38: UK | C38: =COUNTIFS(Base_Assinaturas!$H$2:$H$5001,"Sim",Base_Assinaturas!$G$2:$G$5001,"Até 2024-S1",Base_Assinaturas!$V$2:$V$5001,"UK") | D38: =SUMIFS(Base_Assinaturas!$I$2:$I$5001,Base_Assinaturas!$H$2:$H$5001,"Sim",Base_Assinaturas!$G$2:$G$5001,"Até 2024-S1",Base_Assinaturas!$V$2:$V$5001,"UK") | E38: =IF(C38>0,D38/C38,"") | F38: =COUNTIFS(Base_Assinaturas!$H$2:$H$5001,"Sim",Base_Assinaturas!$G$2:$G$5001,"2024-S2",Base_Assinaturas!$V$2:$V$5001,"UK") | G38: =SUMIFS(Base_Assinaturas!$I$2:$I$5001,Base_Assinaturas!$H$2:$H$5001,"Sim",Base_Assinaturas!$G$2:$G$5001,"2024-S2",Base_Assinaturas!$V$2:$V$5001,"UK") | H38: =IF(F38>0,G38/F38,"") | I38: =IF(AND(ISNUMBER(E38),E38>0),H38/E38,"sem casos antes") | J38: 0.006237 | K38: =C38/C$5 | L38: =F38/F$5 | M38: =(L38-K38)*100
B39: US | C39: =COUNTIFS(Base_Assinaturas!$H$2:$H$5001,"Sim",Base_Assinaturas!$G$2:$G$5001,"Até 2024-S1",Base_Assinaturas!$V$2:$V$5001,"US") | D39: =SUMIFS(Base_Assinaturas!$I$2:$I$5001,Base_Assinaturas!$H$2:$H$5001,"Sim",Base_Assinaturas!$G$2:$G$5001,"Até 2024-S1",Base_Assinaturas!$V$2:$V$5001,"US") | E39: =IF(C39>0,D39/C39,"") | F39: =COUNTIFS(Base_Assinaturas!$H$2:$H$5001,"Sim",Base_Assinaturas!$G$2:$G$5001,"2024-S2",Base_Assinaturas!$V$2:$V$5001,"US") | G39: =SUMIFS(Base_Assinaturas!$I$2:$I$5001,Base_Assinaturas!$H$2:$H$5001,"Sim",Base_Assinaturas!$G$2:$G$5001,"2024-S2",Base_Assinaturas!$V$2:$V$5001,"US") | H39: =IF(F39>0,G39/F39,"") | I39: =IF(AND(ISNUMBER(E39),E39>0),H39/E39,"sem casos antes") | J39: 1e-06 | K39: =C39/C$5 | L39: =F39/F$5 | M39: =(L39-K39)*100
A40: Canal de aquisição | B40: ads | C40: =COUNTIFS(Base_Assinaturas!$H$2:$H$5001,"Sim",Base_Assinaturas!$G$2:$G$5001,"Até 2024-S1",Base_Assinaturas!$W$2:$W$5001,"ads") | D40: =SUMIFS(Base_Assinaturas!$I$2:$I$5001,Base_Assinaturas!$H$2:$H$5001,"Sim",Base_Assinaturas!$G$2:$G$5001,"Até 2024-S1",Base_Assinaturas!$W$2:$W$5001,"ads") | E40: =IF(C40>0,D40/C40,"") | F40: =COUNTIFS(Base_Assinaturas!$H$2:$H$5001,"Sim",Base_Assinaturas!$G$2:$G$5001,"2024-S2",Base_Assinaturas!$W$2:$W$5001,"ads") | G40: =SUMIFS(Base_Assinaturas!$I$2:$I$5001,Base_Assinaturas!$H$2:$H$5001,"Sim",Base_Assinaturas!$G$2:$G$5001,"2024-S2",Base_Assinaturas!$W$2:$W$5001,"ads") | H40: =IF(F40>0,G40/F40,"") | I40: =IF(AND(ISNUMBER(E40),E40>0),H40/E40,"sem casos antes") | J40: 0.013866 | K40: =C40/C$5 | L40: =F40/F$5 | M40: =(L40-K40)*100 | N40: 0.046 | O40: =SUMPRODUCT(L40:L44,E40:E44)
B41: event | C41: =COUNTIFS(Base_Assinaturas!$H$2:$H$5001,"Sim",Base_Assinaturas!$G$2:$G$5001,"Até 2024-S1",Base_Assinaturas!$W$2:$W$5001,"event") | D41: =SUMIFS(Base_Assinaturas!$I$2:$I$5001,Base_Assinaturas!$H$2:$H$5001,"Sim",Base_Assinaturas!$G$2:$G$5001,"Até 2024-S1",Base_Assinaturas!$W$2:$W$5001,"event") | E41: =IF(C41>0,D41/C41,"") | F41: =COUNTIFS(Base_Assinaturas!$H$2:$H$5001,"Sim",Base_Assinaturas!$G$2:$G$5001,"2024-S2",Base_Assinaturas!$W$2:$W$5001,"event") | G41: =SUMIFS(Base_Assinaturas!$I$2:$I$5001,Base_Assinaturas!$H$2:$H$5001,"Sim",Base_Assinaturas!$G$2:$G$5001,"2024-S2",Base_Assinaturas!$W$2:$W$5001,"event") | H41: =IF(F41>0,G41/F41,"") | I41: =IF(AND(ISNUMBER(E41),E41>0),H41/E41,"sem casos antes") | J41: 0.158511 | K41: =C41/C$5 | L41: =F41/F$5 | M41: =(L41-K41)*100
B42: organic | C42: =COUNTIFS(Base_Assinaturas!$H$2:$H$5001,"Sim",Base_Assinaturas!$G$2:$G$5001,"Até 2024-S1",Base_Assinaturas!$W$2:$W$5001,"organic") | D42: =SUMIFS(Base_Assinaturas!$I$2:$I$5001,Base_Assinaturas!$H$2:$H$5001,"Sim",Base_Assinaturas!$G$2:$G$5001,"Até 2024-S1",Base_Assinaturas!$W$2:$W$5001,"organic") | E42: =IF(C42>0,D42/C42,"") | F42: =COUNTIFS(Base_Assinaturas!$H$2:$H$5001,"Sim",Base_Assinaturas!$G$2:$G$5001,"2024-S2",Base_Assinaturas!$W$2:$W$5001,"organic") | G42: =SUMIFS(Base_Assinaturas!$I$2:$I$5001,Base_Assinaturas!$H$2:$H$5001,"Sim",Base_Assinaturas!$G$2:$G$5001,"2024-S2",Base_Assinaturas!$W$2:$W$5001,"organic") | H42: =IF(F42>0,G42/F42,"") | I42: =IF(AND(ISNUMBER(E42),E42>0),H42/E42,"sem casos antes") | J42: 3e-06 | K42: =C42/C$5 | L42: =F42/F$5 | M42: =(L42-K42)*100
B43: other | C43: =COUNTIFS(Base_Assinaturas!$H$2:$H$5001,"Sim",Base_Assinaturas!$G$2:$G$5001,"Até 2024-S1",Base_Assinaturas!$W$2:$W$5001,"other") | D43: =SUMIFS(Base_Assinaturas!$I$2:$I$5001,Base_Assinaturas!$H$2:$H$5001,"Sim",Base_Assinaturas!$G$2:$G$5001,"Até 2024-S1",Base_Assinaturas!$W$2:$W$5001,"other") | E43: =IF(C43>0,D43/C43,"") | F43: =COUNTIFS(Base_Assinaturas!$H$2:$H$5001,"Sim",Base_Assinaturas!$G$2:$G$5001,"2024-S2",Base_Assinaturas!$W$2:$W$5001,"other") | G43: =SUMIFS(Base_Assinaturas!$I$2:$I$5001,Base_Assinaturas!$H$2:$H$5001,"Sim",Base_Assinaturas!$G$2:$G$5001,"2024-S2",Base_Assinaturas!$W$2:$W$5001,"other") | H43: =IF(F43>0,G43/F43,"") | I43: =IF(AND(ISNUMBER(E43),E43>0),H43/E43,"sem casos antes") | J43: 0.000299 | K43: =C43/C$5 | L43: =F43/F$5 | M43: =(L43-K43)*100
B44: partner | C44: =COUNTIFS(Base_Assinaturas!$H$2:$H$5001,"Sim",Base_Assinaturas!$G$2:$G$5001,"Até 2024-S1",Base_Assinaturas!$W$2:$W$5001,"partner") | D44: =SUMIFS(Base_Assinaturas!$I$2:$I$5001,Base_Assinaturas!$H$2:$H$5001,"Sim",Base_Assinaturas!$G$2:$G$5001,"Até 2024-S1",Base_Assinaturas!$W$2:$W$5001,"partner") | E44: =IF(C44>0,D44/C44,"") | F44: =COUNTIFS(Base_Assinaturas!$H$2:$H$5001,"Sim",Base_Assinaturas!$G$2:$G$5001,"2024-S2",Base_Assinaturas!$W$2:$W$5001,"partner") | G44: =SUMIFS(Base_Assinaturas!$I$2:$I$5001,Base_Assinaturas!$H$2:$H$5001,"Sim",Base_Assinaturas!$G$2:$G$5001,"2024-S2",Base_Assinaturas!$W$2:$W$5001,"partner") | H44: =IF(F44>0,G44/F44,"") | I44: =IF(AND(ISNUMBER(E44),E44>0),H44/E44,"sem casos antes") | J44: 0.000345 | K44: =C44/C$5 | L44: =F44/F$5 | M44: =(L44-K44)*100
A46: Leitura: o % que encerra em 30 dias sobe em praticamente todas as categorias de todos os fatores. O mix muda em alguns fatores (idade da conta, indústria, país, canal: p da composição < 0,05), mas a coluna O mostra que essa mudança, sozinha, deixaria a taxa de 2024-S2 perto da antiga (linha TODAS, coluna E).
A47: Coluna O = taxa que 2024-S2 teria se cada categoria mantivesse a taxa antiga e só o mix mudasse. Como fica muito abaixo da taxa real de 2024-S2 (H5), o aumento NÃO vem do mix: é do PERÍODO e atinge todos. A causa está em algo que não aparece nestas tabelas (produto, preço, concorrência, cobrança, onboarding).
A48: p (Fisher) compara S2 vs antes dentro da categoria. Categorias pequenas podem não atingir p < 0,05 mesmo com aumento grande.

Sheet Dezembro
A1: Dezembro de 2024: o que há de diferente nos encerramentos?
A2: Contagens por fórmula sobre Base_Assinaturas. "Esperado" = média diária dos 11 primeiros meses de 2024 escalada pelo número de assinaturas ativas (aproximação).
A4: 1. Encerramentos por dia em dezembro/2024
A5: Dia | B5: Assinaturas encerradas | C5: MRR encerrado (US$)
A6: 45627 | B6: =COUNTIFS(Base_Assinaturas!$D$2:$D$5001,A6) | C6: =SUMIFS(Base_Assinaturas!$F$2:$F$5001,Base_Assinaturas!$D$2:$D$5001,A6)
A7: 45628 | B7: =COUNTIFS(Base_Assinaturas!$D$2:$D$5001,A7) | C7: =SUMIFS(Base_Assinaturas!$F$2:$F$5001,Base_Assinaturas!$D$2:$D$5001,A7)
A8: 45629 | B8: =COUNTIFS(Base_Assinaturas!$D$2:$D$5001,A8) | C8: =SUMIFS(Base_Assinaturas!$F$2:$F$5001,Base_Assinaturas!$D$2:$D$5001,A8)
A9: 45630 | B9: =COUNTIFS(Base_Assinaturas!$D$2:$D$5001,A9) | C9: =SUMIFS(Base_Assinaturas!$F$2:$F$5001,Base_Assinaturas!$D$2:$D$5001,A9)
A10: 45631 | B10: =COUNTIFS(Base_Assinaturas!$D$2:$D$5001,A10) | C10: =SUMIFS(Base_Assinaturas!$F$2:$F$5001,Base_Assinaturas!$D$2:$D$5001,A10)
A11: 45632 | B11: =COUNTIFS(Base_Assinaturas!$D$2:$D$5001,A11) | C11: =SUMIFS(Base_Assinaturas!$F$2:$F$5001,Base_Assinaturas!$D$2:$D$5001,A11)
A12: 45633 | B12: =COUNTIFS(Base_Assinaturas!$D$2:$D$5001,A12) | C12: =SUMIFS(Base_Assinaturas!$F$2:$F$5001,Base_Assinaturas!$D$2:$D$5001,A12)
A13: 45634 | B13: =COUNTIFS(Base_Assinaturas!$D$2:$D$5001,A13) | C13: =SUMIFS(Base_Assinaturas!$F$2:$F$5001,Base_Assinaturas!$D$2:$D$5001,A13)
A14: 45635 | B14: =COUNTIFS(Base_Assinaturas!$D$2:$D$5001,A14) | C14: =SUMIFS(Base_Assinaturas!$F$2:$F$5001,Base_Assinaturas!$D$2:$D$5001,A14)
A15: 45636 | B15: =COUNTIFS(Base_Assinaturas!$D$2:$D$5001,A15) | C15: =SUMIFS(Base_Assinaturas!$F$2:$F$5001,Base_Assinaturas!$D$2:$D$5001,A15)
A16: 45637 | B16: =COUNTIFS(Base_Assinaturas!$D$2:$D$5001,A16) | C16: =SUMIFS(Base_Assinaturas!$F$2:$F$5001,Base_Assinaturas!$D$2:$D$5001,A16)
A17: 45638 | B17: =COUNTIFS(Base_Assinaturas!$D$2:$D$5001,A17) | C17: =SUMIFS(Base_Assinaturas!$F$2:$F$5001,Base_Assinaturas!$D$2:$D$5001,A17)
... A36: 45657 | B36: =COUNTIFS(Base_Assinaturas!$D$2:$D$5001,A36) | C36: =SUMIFS(Base_Assinaturas!$F$2:$F$5001,Base_Assinaturas!$D$2:$D$5001,A36)
A37: Total | B37: =SUM(B6:B36) | C37: =SUM(C6:C36)
A38: Dias 29–31 | B38: =SUM(B34:B36) | C38: =SUM(C34:C36)
A39: Média/dia dias 1–28 | B39: =AVERAGE(B6:B33)
A40: Média/dia dias 29–31 | B40: =AVERAGE(B34:B36)
A43: 2. Fim de mês é comum? % dos encerramentos nos 3 últimos dias do mês
A44: Mês | B44: Encerradas | C44: Nos 3 últimos dias | D44: %
A45: 45292 | B45: =COUNTIFS(Base_Assinaturas!$J$2:$J$5001,A45) | C45: =COUNTIFS(Base_Assinaturas!$J$2:$J$5001,A45,Base_Assinaturas!$L$2:$L$5001,"Sim") | D45: =IF(B45>0,C45/B45,"")
A46: 45323 | B46: =COUNTIFS(Base_Assinaturas!$J$2:$J$5001,A46) | C46: =COUNTIFS(Base_Assinaturas!$J$2:$J$5001,A46,Base_Assinaturas!$L$2:$L$5001,"Sim") | D46: =IF(B46>0,C46/B46,"")
A47: 45352 | B47: =COUNTIFS(Base_Assinaturas!$J$2:$J$5001,A47) | C47: =COUNTIFS(Base_Assinaturas!$J$2:$J$5001,A47,Base_Assinaturas!$L$2:$L$5001,"Sim") | D47: =IF(B47>0,C47/B47,"")
A48: 45383 | B48: =COUNTIFS(Base_Assinaturas!$J$2:$J$5001,A48) | C48: =COUNTIFS(Base_Assinaturas!$J$2:$J$5001,A48,Base_Assinaturas!$L$2:$L$5001,"Sim") | D48: =IF(B48>0,C48/B48,"")
A49: 45413 | B49: =COUNTIFS(Base_Assinaturas!$J$2:$J$5001,A49) | C49: =COUNTIFS(Base_Assinaturas!$J$2:$J$5001,A49,Base_Assinaturas!$L$2:$L$5001,"Sim") | D49: =IF(B49>0,C49/B49,"")
A50: 45444 | B50: =COUNTIFS(Base_Assinaturas!$J$2:$J$5001,A50) | C50: =COUNTIFS(Base_Assinaturas!$J$2:$J$5001,A50,Base_Assinaturas!$L$2:$L$5001,"Sim") | D50: =IF(B50>0,C50/B50,"")
A51: 45474 | B51: =COUNTIFS(Base_Assinaturas!$J$2:$J$5001,A51) | C51: =COUNTIFS(Base_Assinaturas!$J$2:$J$5001,A51,Base_Assinaturas!$L$2:$L$5001,"Sim") | D51: =IF(B51>0,C51/B51,"")
A52: 45505 | B52: =COUNTIFS(Base_Assinaturas!$J$2:$J$5001,A52) | C52: =COUNTIFS(Base_Assinaturas!$J$2:$J$5001,A52,Base_Assinaturas!$L$2:$L$5001,"Sim") | D52: =IF(B52>0,C52/B52,"")
A53: 45536 | B53: =COUNTIFS(Base_Assinaturas!$J$2:$J$5001,A53) | C53: =COUNTIFS(Base_Assinaturas!$J$2:$J$5001,A53,Base_Assinaturas!$L$2:$L$5001,"Sim") | D53: =IF(B53>0,C53/B53,"")
A54: 45566 | B54: =COUNTIFS(Base_Assinaturas!$J$2:$J$5001,A54) | C54: =COUNTIFS(Base_Assinaturas!$J$2:$J$5001,A54,Base_Assinaturas!$L$2:$L$5001,"Sim") | D54: =IF(B54>0,C54/B54,"")
A55: 45597 | B55: =COUNTIFS(Base_Assinaturas!$J$2:$J$5001,A55) | C55: =COUNTIFS(Base_Assinaturas!$J$2:$J$5001,A55,Base_Assinaturas!$L$2:$L$5001,"Sim") | D55: =IF(B55>0,C55/B55,"")
A56: 45627 | B56: =COUNTIFS(Base_Assinaturas!$J$2:$J$5001,A56) | C56: =COUNTIFS(Base_Assinaturas!$J$2:$J$5001,A56,Base_Assinaturas!$L$2:$L$5001,"Sim") | D56: =IF(B56>0,C56/B56,"")
A57: jan–nov/24 | B57: =SUM(B45:B55) | C57: =SUM(C45:C55) | D57: =C57/B57
A58: Referência: 3 dias de ~30 ≈ 10% se os encerramentos fossem espalhados ao longo do mês.
A60: 3. Quem encerrou em dezembro: tempo de vida e perfil
A61: Indicador | B61: Encerradas em dez/24 | C61: Encerradas jan–nov/24
A62: Assinaturas | B62: =COUNTIFS(Base_Assinaturas!$J$2:$J$5001,DATE(2024,12,1)) | C62: =COUNTIFS(Base_Assinaturas!$J$2:$J$5001,">="&DATE(2024,1,1),Base_Assinaturas!$J$2:$J$5001,"<"&DATE(2024,12,1))
A63: % com até 30 dias de vida | B63: =COUNTIFS(Base_Assinaturas!$J$2:$J$5001,DATE(2024,12,1),Base_Assinaturas!$E$2:$E$5001,"<=30")/B62 | C63: =COUNTIFS(Base_Assinaturas!$J$2:$J$5001,">="&DATE(2024,1,1),Base_Assinaturas!$J$2:$J$5001,"<"&DATE(2024,12,1),Base_Assinaturas!$E$2:$E$5001,"<=30")/C62
A64: % iniciadas no mesmo mês | B64: =COUNTIFS(Base_Assinaturas!$J$2:$J$5001,DATE(2024,12,1),Base_Assinaturas!$C$2:$C$5001,">="&DATE(2024,12,1))/B62
A65: % trial | B65: =COUNTIFS(Base_Assinaturas!$J$2:$J$5001,DATE(2024,12,1),Base_Assinaturas!$O$2:$O$5001,"Trial")/B62 | C65: =COUNTIFS(Base_Assinaturas!$J$2:$J$5001,">="&DATE(2024,1,1),Base_Assinaturas!$J$2:$J$5001,"<"&DATE(2024,12,1),Base_Assinaturas!$O$2:$O$5001,"Trial")/C62
A66: % Enterprise | B66: =COUNTIFS(Base_Assinaturas!$J$2:$J$5001,DATE(2024,12,1),Base_Assinaturas!$M$2:$M$5001,"Enterprise")/B62 | C66: =COUNTIFS(Base_Assinaturas!$J$2:$J$5001,">="&DATE(2024,1,1),Base_Assinaturas!$J$2:$J$5001,"<"&DATE(2024,12,1),Base_Assinaturas!$M$2:$M$5001,"Enterprise")/C62
A67: MRR encerrado (US$) | B67: =SUMIFS(Base_Assinaturas!$F$2:$F$5001,Base_Assinaturas!$J$2:$J$5001,DATE(2024,12,1)) | C67: =SUMIFS(Base_Assinaturas!$F$2:$F$5001,Base_Assinaturas!$J$2:$J$5001,">="&DATE(2024,1,1),Base_Assinaturas!$J$2:$J$5001,"<"&DATE(2024,12,1))
A69: Leitura: dezembro mistura dois efeitos. (1) Muitas assinaturas novas encerrando em poucos dias (efeito do período). (2) Concentração anormal em 29–31/12, que pode ser fechamento de ano / renovação anual ou corte da extração: confirmar com a área antes de tratar como churn de cliente.

Sheet Sinais_no_tempo
A1: Sinais no tempo: churn subiu; suporte e uso não acompanharam
A2: Tudo por fórmula sobre as bases. Datas de ticket e de uso têm problemas de coerência com a conta (ver 01_Evidencias); aqui olhamos só a tendência do mês, sem ligar a conta.
A4: Mês | B4: Assinaturas iniciadas | C4: Iniciadas que encerraram em 30 dias | D4: % encerra em 30 dias (coorte do mês) | E4: Tickets | F4: Satisfação média | G4: Resolução média (h) | H4: 1ª resposta média (min) | I4: % escalados | J4: Uso total (usage_count) | K4: Erros por 100 usos
A5: 44927 | B5: =COUNTIFS(Base_Assinaturas!$C$2:$C$5001,">="&A5,Base_Assinaturas!$C$2:$C$5001,"<"&EDATE(A5,1)) | C5: =SUMIFS(Base_Assinaturas!$I$2:$I$5001,Base_Assinaturas!$C$2:$C$5001,">="&A5,Base_Assinaturas!$C$2:$C$5001,"<"&EDATE(A5,1)) | D5: =IF(B5>0,C5/B5,"") | E5: =COUNTIFS(Base_Tickets!$C$2:$C$2001,A5) | F5: =IFERROR(AVERAGEIFS(Base_Tickets!$F$2:$F$2001,Base_Tickets!$C$2:$C$2001,A5),"") | G5: =IFERROR(AVERAGEIFS(Base_Tickets!$D$2:$D$2001,Base_Tickets!$C$2:$C$2001,A5),"") | H5: =IFERROR(AVERAGEIFS(Base_Tickets!$E$2:$E$2001,Base_Tickets!$C$2:$C$2001,A5),"") | I5: =IFERROR(AVERAGEIFS(Base_Tickets!$G$2:$G$2001,Base_Tickets!$C$2:$C$2001,A5),"") | J5: =SUMIFS(Base_Uso!$C$2:$C$25001,Base_Uso!$B$2:$B$25001,A5) | K5: =IFERROR(SUMIFS(Base_Uso!$D$2:$D$25001,Base_Uso!$B$2:$B$25001,A5)/J5*100,"")
A6: 44958 | B6: =COUNTIFS(Base_Assinaturas!$C$2:$C$5001,">="&A6,Base_Assinaturas!$C$2:$C$5001,"<"&EDATE(A6,1)) | C6: =SUMIFS(Base_Assinaturas!$I$2:$I$5001,Base_Assinaturas!$C$2:$C$5001,">="&A6,Base_Assinaturas!$C$2:$C$5001,"<"&EDATE(A6,1)) | D6: =IF(B6>0,C6/B6,"") | E6: =COUNTIFS(Base_Tickets!$C$2:$C$2001,A6) | F6: =IFERROR(AVERAGEIFS(Base_Tickets!$F$2:$F$2001,Base_Tickets!$C$2:$C$2001,A6),"") | G6: =IFERROR(AVERAGEIFS(Base_Tickets!$D$2:$D$2001,Base_Tickets!$C$2:$C$2001,A6),"") | H6: =IFERROR(AVERAGEIFS(Base_Tickets!$E$2:$E$2001,Base_Tickets!$C$2:$C$2001,A6),"") | I6: =IFERROR(AVERAGEIFS(Base_Tickets!$G$2:$G$2001,Base_Tickets!$C$2:$C$2001,A6),"") | J6: =SUMIFS(Base_Uso!$C$2:$C$25001,Base_Uso!$B$2:$B$25001,A6) | K6: =IFERROR(SUMIFS(Base_Uso!$D$2:$D$25001,Base_Uso!$B$2:$B$25001,A6)/J6*100,"")
A7: 44986 | B7: =COUNTIFS(Base_Assinaturas!$C$2:$C$5001,">="&A7,Base_Assinaturas!$C$2:$C$5001,"<"&EDATE(A7,1)) | C7: =SUMIFS(Base_Assinaturas!$I$2:$I$5001,Base_Assinaturas!$C$2:$C$5001,">="&A7,Base_Assinaturas!$C$2:$C$5001,"<"&EDATE(A7,1)) | D7: =IF(B7>0,C7/B7,"") | E7: =COUNTIFS(Base_Tickets!$C$2:$C$2001,A7) | F7: =IFERROR(AVERAGEIFS(Base_Tickets!$F$2:$F$2001,Base_Tickets!$C$2:$C$2001,A7),"") | G7: =IFERROR(AVERAGEIFS(Base_Tickets!$D$2:$D$2001,Base_Tickets!$C$2:$C$2001,A7),"") | H7: =IFERROR(AVERAGEIFS(Base_Tickets!$E$2:$E$2001,Base_Tickets!$C$2:$C$2001,A7),"") | I7: =IFERROR(AVERAGEIFS(Base_Tickets!$G$2:$G$2001,Base_Tickets!$C$2:$C$2001,A7),"") | J7: =SUMIFS(Base_Uso!$C$2:$C$25001,Base_Uso!$B$2:$B$25001,A7) | K7: =IFERROR(SUMIFS(Base_Uso!$D$2:$D$25001,Base_Uso!$B$2:$B$25001,A7)/J7*100,"")
A8: 45017 | B8: =COUNTIFS(Base_Assinaturas!$C$2:$C$5001,">="&A8,Base_Assinaturas!$C$2:$C$5001,"<"&EDATE(A8,1)) | C8: =SUMIFS(Base_Assinaturas!$I$2:$I$5001,Base_Assinaturas!$C$2:$C$5001,">="&A8,Base_Assinaturas!$C$2:$C$5001,"<"&EDATE(A8,1)) | D8: =IF(B8>0,C8/B8,"") | E8: =COUNTIFS(Base_Tickets!$C$2:$C$2001,A8) | F8: =IFERROR(AVERAGEIFS(Base_Tickets!$F$2:$F$2001,Base_Tickets!$C$2:$C$2001,A8),"") | G8: =IFERROR(AVERAGEIFS(Base_Tickets!$D$2:$D$2001,Base_Tickets!$C$2:$C$2001,A8),"") | H8: =IFERROR(AVERAGEIFS(Base_Tickets!$E$2:$E$2001,Base_Tickets!$C$2:$C$2001,A8),"") | I8: =IFERROR(AVERAGEIFS(Base_Tickets!$G$2:$G$2001,Base_Tickets!$C$2:$C$2001,A8),"") | J8: =SUMIFS(Base_Uso!$C$2:$C$25001,Base_Uso!$B$2:$B$25001,A8) | K8: =IFERROR(SUMIFS(Base_Uso!$D$2:$D$25001,Base_Uso!$B$2:$B$25001,A8)/J8*100,"")
A9: 45047 | B9: =COUNTIFS(Base_Assinaturas!$C$2:$C$5001,">="&A9,Base_Assinaturas!$C$2:$C$5001,"<"&EDATE(A9,1)) | C9: =SUMIFS(Base_Assinaturas!$I$2:$I$5001,Base_Assinaturas!$C$2:$C$5001,">="&A9,Base_Assinaturas!$C$2:$C$5001,"<"&EDATE(A9,1)) | D9: =IF(B9>0,C9/B9,"") | E9: =COUNTIFS(Base_Tickets!$C$2:$C$2001,A9) | F9: =IFERROR(AVERAGEIFS(Base_Tickets!$F$2:$F$2001,Base_Tickets!$C$2:$C$2001,A9),"") | G9: =IFERROR(AVERAGEIFS(Base_Tickets!$D$2:$D$2001,Base_Tickets!$C$2:$C$2001,A9),"") | H9: =IFERROR(AVERAGEIFS(Base_Tickets!$E$2:$E$2001,Base_Tickets!$C$2:$C$2001,A9),"") | I9: =IFERROR(AVERAGEIFS(Base_Tickets!$G$2:$G$2001,Base_Tickets!$C$2:$C$2001,A9),"") | J9: =SUMIFS(Base_Uso!$C$2:$C$25001,Base_Uso!$B$2:$B$25001,A9) | K9: =IFERROR(SUMIFS(Base_Uso!$D$2:$D$25001,Base_Uso!$B$2:$B$25001,A9)/J9*100,"")
A10: 45078 | B10: =COUNTIFS(Base_Assinaturas!$C$2:$C$5001,">="&A10,Base_Assinaturas!$C$2:$C$5001,"<"&EDATE(A10,1)) | C10: =SUMIFS(Base_Assinaturas!$I$2:$I$5001,Base_Assinaturas!$C$2:$C$5001,">="&A10,Base_Assinaturas!$C$2:$C$5001,"<"&EDATE(A10,1)) | D10: =IF(B10>0,C10/B10,"") | E10: =COUNTIFS(Base_Tickets!$C$2:$C$2001,A10) | F10: =IFERROR(AVERAGEIFS(Base_Tickets!$F$2:$F$2001,Base_Tickets!$C$2:$C$2001,A10),"") | G10: =IFERROR(AVERAGEIFS(Base_Tickets!$D$2:$D$2001,Base_Tickets!$C$2:$C$2001,A10),"") | H10: =IFERROR(AVERAGEIFS(Base_Tickets!$E$2:$E$2001,Base_Tickets!$C$2:$C$2001,A10),"") | I10: =IFERROR(AVERAGEIFS(Base_Tickets!$G$2:$G$2001,Base_Tickets!$C$2:$C$2001,A10),"") | J10: =SUMIFS(Base_Uso!$C$2:$C$25001,Base_Uso!$B$2:$B$25001,A10) | K10: =IFERROR(SUMIFS(Base_Uso!$D$2:$D$25001,Base_Uso!$B$2:$B$25001,A10)/J10*100,"")
A11: 45108 | B11: =COUNTIFS(Base_Assinaturas!$C$2:$C$5001,">="&A11,Base_Assinaturas!$C$2:$C$5001,"<"&EDATE(A11,1)) | C11: =SUMIFS(Base_Assinaturas!$I$2:$I$5001,Base_Assinaturas!$C$2:$C$5001,">="&A11,Base_Assinaturas!$C$2:$C$5001,"<"&EDATE(A11,1)) | D11: =IF(B11>0,C11/B11,"") | E11: =COUNTIFS(Base_Tickets!$C$2:$C$2001,A11) | F11: =IFERROR(AVERAGEIFS(Base_Tickets!$F$2:$F$2001,Base_Tickets!$C$2:$C$2001,A11),"") | G11: =IFERROR(AVERAGEIFS(Base_Tickets!$D$2:$D$2001,Base_Tickets!$C$2:$C$2001,A11),"") | H11: =IFERROR(AVERAGEIFS(Base_Tickets!$E$2:$E$2001,Base_Tickets!$C$2:$C$2001,A11),"") | I11: =IFERROR(AVERAGEIFS(Base_Tickets!$G$2:$G$2001,Base_Tickets!$C$2:$C$2001,A11),"") | J11: =SUMIFS(Base_Uso!$C$2:$C$25001,Base_Uso!$B$2:$B$25001,A11) | K11: =IFERROR(SUMIFS(Base_Uso!$D$2:$D$25001,Base_Uso!$B$2:$B$25001,A11)/J11*100,"")
A12: 45139 | B12: =COUNTIFS(Base_Assinaturas!$C$2:$C$5001,">="&A12,Base_Assinaturas!$C$2:$C$5001,"<"&EDATE(A12,1)) | C12: =SUMIFS(Base_Assinaturas!$I$2:$I$5001,Base_Assinaturas!$C$2:$C$5001,">="&A12,Base_Assinaturas!$C$2:$C$5001,"<"&EDATE(A12,1)) | D12: =IF(B12>0,C12/B12,"") | E12: =COUNTIFS(Base_Tickets!$C$2:$C$2001,A12) | F12: =IFERROR(AVERAGEIFS(Base_Tickets!$F$2:$F$2001,Base_Tickets!$C$2:$C$2001,A12),"") | G12: =IFERROR(AVERAGEIFS(Base_Tickets!$D$2:$D$2001,Base_Tickets!$C$2:$C$2001,A12),"") | H12: =IFERROR(AVERAGEIFS(Base_Tickets!$E$2:$E$2001,Base_Tickets!$C$2:$C$2001,A12),"") | I12: =IFERROR(AVERAGEIFS(Base_Tickets!$G$2:$G$2001,Base_Tickets!$C$2:$C$2001,A12),"") | J12: =SUMIFS(Base_Uso!$C$2:$C$25001,Base_Uso!$B$2:$B$25001,A12) | K12: =IFERROR(SUMIFS(Base_Uso!$D$2:$D$25001,Base_Uso!$B$2:$B$25001,A12)/J12*100,"")
A13: 45170 | B13: =COUNTIFS(Base_Assinaturas!$C$2:$C$5001,">="&A13,Base_Assinaturas!$C$2:$C$5001,"<"&EDATE(A13,1)) | C13: =SUMIFS(Base_Assinaturas!$I$2:$I$5001,Base_Assinaturas!$C$2:$C$5001,">="&A13,Base_Assinaturas!$C$2:$C$5001,"<"&EDATE(A13,1)) | D13: =IF(B13>0,C13/B13,"") | E13: =COUNTIFS(Base_Tickets!$C$2:$C$2001,A13) | F13: =IFERROR(AVERAGEIFS(Base_Tickets!$F$2:$F$2001,Base_Tickets!$C$2:$C$2001,A13),"") | G13: =IFERROR(AVERAGEIFS(Base_Tickets!$D$2:$D$2001,Base_Tickets!$C$2:$C$2001,A13),"") | H13: =IFERROR(AVERAGEIFS(Base_Tickets!$E$2:$E$2001,Base_Tickets!$C$2:$C$2001,A13),"") | I13: =IFERROR(AVERAGEIFS(Base_Tickets!$G$2:$G$2001,Base_Tickets!$C$2:$C$2001,A13),"") | J13: =SUMIFS(Base_Uso!$C$2:$C$25001,Base_Uso!$B$2:$B$25001,A13) | K13: =IFERROR(SUMIFS(Base_Uso!$D$2:$D$25001,Base_Uso!$B$2:$B$25001,A13)/J13*100,"")
A14: 45200 | B14: =COUNTIFS(Base_Assinaturas!$C$2:$C$5001,">="&A14,Base_Assinaturas!$C$2:$C$5001,"<"&EDATE(A14,1)) | C14: =SUMIFS(Base_Assinaturas!$I$2:$I$5001,Base_Assinaturas!$C$2:$C$5001,">="&A14,Base_Assinaturas!$C$2:$C$5001,"<"&EDATE(A14,1)) | D14: =IF(B14>0,C14/B14,"") | E14: =COUNTIFS(Base_Tickets!$C$2:$C$2001,A14) | F14: =IFERROR(AVERAGEIFS(Base_Tickets!$F$2:$F$2001,Base_Tickets!$C$2:$C$2001,A14),"") | G14: =IFERROR(AVERAGEIFS(Base_Tickets!$D$2:$D$2001,Base_Tickets!$C$2:$C$2001,A14),"") | H14: =IFERROR(AVERAGEIFS(Base_Tickets!$E$2:$E$2001,Base_Tickets!$C$2:$C$2001,A14),"") | I14: =IFERROR(AVERAGEIFS(Base_Tickets!$G$2:$G$2001,Base_Tickets!$C$2:$C$2001,A14),"") | J14: =SUMIFS(Base_Uso!$C$2:$C$25001,Base_Uso!$B$2:$B$25001,A14) | K14: =IFERROR(SUMIFS(Base_Uso!$D$2:$D$25001,Base_Uso!$B$2:$B$25001,A14)/J14*100,"")
A15: 45231 | B15: =COUNTIFS(Base_Assinaturas!$C$2:$C$5001,">="&A15,Base_Assinaturas!$C$2:$C$5001,"<"&EDATE(A15,1)) | C15: =SUMIFS(Base_Assinaturas!$I$2:$I$5001,Base_Assinaturas!$C$2:$C$5001,">="&A15,Base_Assinaturas!$C$2:$C$5001,"<"&EDATE(A15,1)) | D15: =IF(B15>0,C15/B15,"") | E15: =COUNTIFS(Base_Tickets!$C$2:$C$2001,A15) | F15: =IFERROR(AVERAGEIFS(Base_Tickets!$F$2:$F$2001,Base_Tickets!$C$2:$C$2001,A15),"") | G15: =IFERROR(AVERAGEIFS(Base_Tickets!$D$2:$D$2001,Base_Tickets!$C$2:$C$2001,A15),"") | H15: =IFERROR(AVERAGEIFS(Base_Tickets!$E$2:$E$2001,Base_Tickets!$C$2:$C$2001,A15),"") | I15: =IFERROR(AVERAGEIFS(Base_Tickets!$G$2:$G$2001,Base_Tickets!$C$2:$C$2001,A15),"") | J15: =SUMIFS(Base_Uso!$C$2:$C$25001,Base_Uso!$B$2:$B$25001,A15) | K15: =IFERROR(SUMIFS(Base_Uso!$D$2:$D$25001,Base_Uso!$B$2:$B$25001,A15)/J15*100,"")
A16: 45261 | B16: =COUNTIFS(Base_Assinaturas!$C$2:$C$5001,">="&A16,Base_Assinaturas!$C$2:$C$5001,"<"&EDATE(A16,1)) | C16: =SUMIFS(Base_Assinaturas!$I$2:$I$5001,Base_Assinaturas!$C$2:$C$5001,">="&A16,Base_Assinaturas!$C$2:$C$5001,"<"&EDATE(A16,1)) | D16: =IF(B16>0,C16/B16,"") | E16: =COUNTIFS(Base_Tickets!$C$2:$C$2001,A16) | F16: =IFERROR(AVERAGEIFS(Base_Tickets!$F$2:$F$2001,Base_Tickets!$C$2:$C$2001,A16),"") | G16: =IFERROR(AVERAGEIFS(Base_Tickets!$D$2:$D$2001,Base_Tickets!$C$2:$C$2001,A16),"") | H16: =IFERROR(AVERAGEIFS(Base_Tickets!$E$2:$E$2001,Base_Tickets!$C$2:$C$2001,A16),"") | I16: =IFERROR(AVERAGEIFS(Base_Tickets!$G$2:$G$2001,Base_Tickets!$C$2:$C$2001,A16),"") | J16: =SUMIFS(Base_Uso!$C$2:$C$25001,Base_Uso!$B$2:$B$25001,A16) | K16: =IFERROR(SUMIFS(Base_Uso!$D$2:$D$25001,Base_Uso!$B$2:$B$25001,A16)/J16*100,"")
... A27: 45597 | B27: =COUNTIFS(Base_Assinaturas!$C$2:$C$5001,">="&A27,Base_Assinaturas!$C$2:$C$5001,"<"&EDATE(A27,1)) | C27: =SUMIFS(Base_Assinaturas!$I$2:$I$5001,Base_Assinaturas!$C$2:$C$5001,">="&A27,Base_Assinaturas!$C$2:$C$5001,"<"&EDATE(A27,1)) | D27: =IF(B27>0,C27/B27,"") | E27: =COUNTIFS(Base_Tickets!$C$2:$C$2001,A27) | F27: =IFERROR(AVERAGEIFS(Base_Tickets!$F$2:$F$2001,Base_Tickets!$C$2:$C$2001,A27),"") | G27: =IFERROR(AVERAGEIFS(Base_Tickets!$D$2:$D$2001,Base_Tickets!$C$2:$C$2001,A27),"") | H27: =IFERROR(AVERAGEIFS(Base_Tickets!$E$2:$E$2001,Base_Tickets!$C$2:$C$2001,A27),"") | I27: =IFERROR(AVERAGEIFS(Base_Tickets!$G$2:$G$2001,Base_Tickets!$C$2:$C$2001,A27),"") | J27: =SUMIFS(Base_Uso!$C$2:$C$25001,Base_Uso!$B$2:$B$25001,A27) | K27: =IFERROR(SUMIFS(Base_Uso!$D$2:$D$25001,Base_Uso!$B$2:$B$25001,A27)/J27*100,"")
A28: Coortes até nov/24 (dez/24 ainda não teve 30 dias). Leitura: % que encerra em 30 dias sobe a partir de jul/24; satisfação, tempos de atendimento, escalação, uso e erros ficam estáveis. O CS está certo (satisfação ok) e o produto também (uso não caiu), mas nenhum desses indicadores acompanha o churn.

Sheet Subconjunto_limpo
A1: Subconjunto limpo: 100 contas em que as 3 marcações concordam
A2: 50 contas com churn nas 3 definições (churn_flag, evento e assinatura encerrada) vs 50 sem churn em nenhuma. Médias por fórmula; p = permutação (5.000 sorteios) entre os dois grupos limpos.
A4: Indicador | B4: Churn (3 concordam) | C4: Ativa (3 concordam) | D4: Divergente (400) | E4: Diferença (churn − ativa) | F4: p (churn vs ativa) | G4: Leitura
A5: Contas | B5: =COUNTIFS(Base_Contas!$B$2:$B$501,"Churn (3 concordam)") | C5: =COUNTIFS(Base_Contas!$B$2:$B$501,"Ativa (3 concordam)") | D5: =COUNTIFS(Base_Contas!$B$2:$B$501,"Divergente")
A6: MRR ativo (US$) | B6: =IFERROR(AVERAGEIFS(Base_Contas!$H$2:$H$501,Base_Contas!$B$2:$B$501,"Churn (3 concordam)"),"") | C6: =IFERROR(AVERAGEIFS(Base_Contas!$H$2:$H$501,Base_Contas!$B$2:$B$501,"Ativa (3 concordam)"),"") | D6: =IFERROR(AVERAGEIFS(Base_Contas!$H$2:$H$501,Base_Contas!$B$2:$B$501,"Divergente"),"") | E6: =B6-C6 | F6: 0.2531 | G6: =IF(F6<0.05,"Diferença além do acaso","Sem diferença detectável")
A7: Assinaturas por conta | B7: =IFERROR(AVERAGEIFS(Base_Contas!$I$2:$I$501,Base_Contas!$B$2:$B$501,"Churn (3 concordam)"),"") | C7: =IFERROR(AVERAGEIFS(Base_Contas!$I$2:$I$501,Base_Contas!$B$2:$B$501,"Ativa (3 concordam)"),"") | D7: =IFERROR(AVERAGEIFS(Base_Contas!$I$2:$I$501,Base_Contas!$B$2:$B$501,"Divergente"),"") | E7: =B7-C7 | F7: 0.008 | G7: =IF(F7<0.05,"Diferença além do acaso","Sem diferença detectável")
A8: % das assinaturas iniciadas em 2024-S2 | B8: =IFERROR(AVERAGEIFS(Base_Contas!$J$2:$J$501,Base_Contas!$B$2:$B$501,"Churn (3 concordam)"),"") | C8: =IFERROR(AVERAGEIFS(Base_Contas!$J$2:$J$501,Base_Contas!$B$2:$B$501,"Ativa (3 concordam)"),"") | D8: =IFERROR(AVERAGEIFS(Base_Contas!$J$2:$J$501,Base_Contas!$B$2:$B$501,"Divergente"),"") | E8: =B8-C8 | F8: 0.2354 | G8: =IF(F8<0.05,"Diferença além do acaso","Sem diferença detectável")
A9: Meses desde o cadastro | B9: =IFERROR(AVERAGEIFS(Base_Contas!$K$2:$K$501,Base_Contas!$B$2:$B$501,"Churn (3 concordam)"),"") | C9: =IFERROR(AVERAGEIFS(Base_Contas!$K$2:$K$501,Base_Contas!$B$2:$B$501,"Ativa (3 concordam)"),"") | D9: =IFERROR(AVERAGEIFS(Base_Contas!$K$2:$K$501,Base_Contas!$B$2:$B$501,"Divergente"),"") | E9: =B9-C9 | F9: 0.4213 | G9: =IF(F9<0.05,"Diferença além do acaso","Sem diferença detectável")
A10: Seats (cadastro) | B10: =IFERROR(AVERAGEIFS(Base_Contas!$L$2:$L$501,Base_Contas!$B$2:$B$501,"Churn (3 concordam)"),"") | C10: =IFERROR(AVERAGEIFS(Base_Contas!$L$2:$L$501,Base_Contas!$B$2:$B$501,"Ativa (3 concordam)"),"") | D10: =IFERROR(AVERAGEIFS(Base_Contas!$L$2:$L$501,Base_Contas!$B$2:$B$501,"Divergente"),"") | E10: =B10-C10 | F10: 0.2947 | G10: =IF(F10<0.05,"Diferença além do acaso","Sem diferença detectável")
A11: Uso total (usage_count) | B11: =IFERROR(AVERAGEIFS(Base_Contas!$M$2:$M$501,Base_Contas!$B$2:$B$501,"Churn (3 concordam)"),"") | C11: =IFERROR(AVERAGEIFS(Base_Contas!$M$2:$M$501,Base_Contas!$B$2:$B$501,"Ativa (3 concordam)"),"") | D11: =IFERROR(AVERAGEIFS(Base_Contas!$M$2:$M$501,Base_Contas!$B$2:$B$501,"Divergente"),"") | E11: =B11-C11 | F11: 0.0306 | G11: =IF(F11<0.05,"Diferença além do acaso","Sem diferença detectável")
A12: Erros por 100 usos | B12: =IFERROR(AVERAGEIFS(Base_Contas!$N$2:$N$501,Base_Contas!$B$2:$B$501,"Churn (3 concordam)"),"") | C12: =IFERROR(AVERAGEIFS(Base_Contas!$N$2:$N$501,Base_Contas!$B$2:$B$501,"Ativa (3 concordam)"),"") | D12: =IFERROR(AVERAGEIFS(Base_Contas!$N$2:$N$501,Base_Contas!$B$2:$B$501,"Divergente"),"") | E12: =B12-C12 | F12: 0.3667 | G12: =IF(F12<0.05,"Diferença além do acaso","Sem diferença detectável")
A13: Tickets por conta | B13: =IFERROR(AVERAGEIFS(Base_Contas!$O$2:$O$501,Base_Contas!$B$2:$B$501,"Churn (3 concordam)"),"") | C13: =IFERROR(AVERAGEIFS(Base_Contas!$O$2:$O$501,Base_Contas!$B$2:$B$501,"Ativa (3 concordam)"),"") | D13: =IFERROR(AVERAGEIFS(Base_Contas!$O$2:$O$501,Base_Contas!$B$2:$B$501,"Divergente"),"") | E13: =B13-C13 | F13: 0.6215 | G13: =IF(F13<0.05,"Diferença além do acaso","Sem diferença detectável")
A14: Satisfação média | B14: =IFERROR(AVERAGEIFS(Base_Contas!$P$2:$P$501,Base_Contas!$B$2:$B$501,"Churn (3 concordam)"),"") | C14: =IFERROR(AVERAGEIFS(Base_Contas!$P$2:$P$501,Base_Contas!$B$2:$B$501,"Ativa (3 concordam)"),"") | D14: =IFERROR(AVERAGEIFS(Base_Contas!$P$2:$P$501,Base_Contas!$B$2:$B$501,"Divergente"),"") | E14: =B14-C14 | F14: 0.8612 | G14: =IF(F14<0.05,"Diferença além do acaso","Sem diferença detectável")
A15: % com upgrade | B15: =IFERROR(AVERAGEIFS(Base_Contas!$Q$2:$Q$501,Base_Contas!$B$2:$B$501,"Churn (3 concordam)"),"") | C15: =IFERROR(AVERAGEIFS(Base_Contas!$Q$2:$Q$501,Base_Contas!$B$2:$B$501,"Ativa (3 concordam)"),"") | D15: =IFERROR(AVERAGEIFS(Base_Contas!$Q$2:$Q$501,Base_Contas!$B$2:$B$501,"Divergente"),"") | E15: =B15-C15 | F15: 0.8352 | G15: =IF(F15<0.05,"Diferença além do acaso","Sem diferença detectável")
A16: % com downgrade | B16: =IFERROR(AVERAGEIFS(Base_Contas!$R$2:$R$501,Base_Contas!$B$2:$B$501,"Churn (3 concordam)"),"") | C16: =IFERROR(AVERAGEIFS(Base_Contas!$R$2:$R$501,Base_Contas!$B$2:$B$501,"Ativa (3 concordam)"),"") | D16: =IFERROR(AVERAGEIFS(Base_Contas!$R$2:$R$501,Base_Contas!$B$2:$B$501,"Divergente"),"") | E16: =B16-C16 | F16: 0.5323 | G16: =IF(F16<0.05,"Diferença além do acaso","Sem diferença detectável")
A17: % DevTools | B17: =IFERROR(AVERAGEIFS(Base_Contas!$S$2:$S$501,Base_Contas!$B$2:$B$501,"Churn (3 concordam)"),"") | C17: =IFERROR(AVERAGEIFS(Base_Contas!$S$2:$S$501,Base_Contas!$B$2:$B$501,"Ativa (3 concordam)"),"") | D17: =IFERROR(AVERAGEIFS(Base_Contas!$S$2:$S$501,Base_Contas!$B$2:$B$501,"Divergente"),"") | E17: =B17-C17 | F17: 0.0038 | G17: =IF(F17<0.05,"Diferença além do acaso","Sem diferença detectável")
A18: % canal partner | B18: =IFERROR(AVERAGEIFS(Base_Contas!$T$2:$T$501,Base_Contas!$B$2:$B$501,"Churn (3 concordam)"),"") | C18: =IFERROR(AVERAGEIFS(Base_Contas!$T$2:$T$501,Base_Contas!$B$2:$B$501,"Ativa (3 concordam)"),"") | D18: =IFERROR(AVERAGEIFS(Base_Contas!$T$2:$T$501,Base_Contas!$B$2:$B$501,"Divergente"),"") | E18: =B18-C18 | F18: 0.0264 | G18: =IF(F18<0.05,"Diferença além do acaso","Sem diferença detectável")
A20: churn_flag por indústria na base toda (500 contas)
A21: Indústria | B21: Contas | C21: Com churn_flag | D21: % churn_flag
A22: Cybersecurity | B22: =COUNTIFS(Base_Contas!$C$2:$C$501,A22) | C22: =COUNTIFS(Base_Contas!$C$2:$C$501,A22,Base_Contas!$E$2:$E$501,TRUE) | D22: =C22/B22
A23: DevTools | B23: =COUNTIFS(Base_Contas!$C$2:$C$501,A23) | C23: =COUNTIFS(Base_Contas!$C$2:$C$501,A23,Base_Contas!$E$2:$E$501,TRUE) | D23: =C23/B23
A24: EdTech | B24: =COUNTIFS(Base_Contas!$C$2:$C$501,A24) | C24: =COUNTIFS(Base_Contas!$C$2:$C$501,A24,Base_Contas!$E$2:$E$501,TRUE) | D24: =C24/B24
A25: FinTech | B25: =COUNTIFS(Base_Contas!$C$2:$C$501,A25) | C25: =COUNTIFS(Base_Contas!$C$2:$C$501,A25,Base_Contas!$E$2:$E$501,TRUE) | D25: =C25/B25
A26: HealthTech | B26: =COUNTIFS(Base_Contas!$C$2:$C$501,A26) | C26: =COUNTIFS(Base_Contas!$C$2:$C$501,A26,Base_Contas!$E$2:$E$501,TRUE) | D26: =C26/B26
A28: Leitura: as contas "limpas" são parecidas em receita, erros, tickets e satisfação. Diferenças que aparecem: mais assinaturas e mais uso no grupo churn (mecânico: quem tem mais assinaturas tem mais chance de ter uma encerrada e soma mais registros de uso), concentração em DevTools e pouca presença do canal partner.
A29: Cuidado: o grupo "churn" exige churn_flag = TRUE, e o churn_flag já é concentrado em DevTools na base toda (tabela acima). Como receita (P1/P2) e eventos (S1) NÃO mostram DevTools diferente (02_Triangulacao), isso é efeito do churn_flag, não confirmação independente.
A30: Amostra pequena (50 vs 50): serve para checar o que foi achado na base toda, não para descobrir causas novas.

Sheet Base_Assinaturas
A1: subscription_id | B1: account_id | C1: start_date | D1: end_date | E1: duracao_dias | F1: mrr_amount | G1: coorte | H1: observavel_30d | I1: encerrou_30d | J1: mes_fim | K1: dia_fim | L1: ultimos_3_dias_mes | M1: f_plano | N1: f_cobranca | O1: f_trial | P1: f_auto_renew | Q1: f_upgrade | R1: f_downgrade | S1: f_seats | T1: f_idade_conta | U1: f_industria | V1: f_pais | W1: f_canal
A2: S-8cec59 | B2: A-3c1a3f | C2: 45283 | D2: 45394 | E2: 111 | F2: 2786 | G2: Até 2024-S1 | H2: Sim | I2: 0 | J2: 45383 | K2: 12 | L2: Não | M2: Enterprise | N2: monthly | O2: Pago | P2: Sim | Q2: Não | R2: Não | S2: 6–15 | T2: 91–180 dias | U2: DevTools | V2: UK | W2: event
A3: S-0f6f44 | B3: A-9b9fe9 | C3: 45454 | E3: 203 | F3: 833 | G3: Até 2024-S1 | H3: Sim | I3: 0 | M3: Pro | N3: monthly | O3: Pago | P3: Sim | Q3: Não | R3: Não | S3: 16–40 | T3: 181–365 dias | U3: EdTech | V3: AU | W3: other
A4: S-51c0d1 | B4: A-659280 | C4: 45621 | E4: 36 | F4: 0 | G4: 2024-S2 | H4: Sim | I4: 0 | M4: Enterprise | N4: annual | O4: Trial | P4: Não | Q4: Sim | R4: Não | S4: 41+ | T4: Mais de 365 dias | U4: FinTech | V4: IN | W4: event
A5: S-f81687 | B5: A-e7a1e2 | C5: 45619 | D5: 45639 | E5: 20 | F5: 995 | G5: 2024-S2 | H5: Sim | I5: 1 | J5: 45627 | K5: 13 | L5: Não | M5: Enterprise | N5: monthly | O5: Pago | P5: Sim | Q5: Não | R5: Não | S5: 1–5 | T5: 91–180 dias | U5: Cybersecurity | V5: US | W5: event
A6: S-cff5a2 | B6: A-ba6516 | C6: 45301 | E6: 356 | F6: 5373 | G6: Até 2024-S1 | H6: Sim | I6: 0 | M6: Enterprise | N6: monthly | O6: Pago | P6: Sim | Q6: Não | R6: Não | S6: 16–40 | T6: 31–90 dias | U6: FinTech | V6: US | W6: ads
A7: S-4b9b13 | B7: A-fa2041 | C7: 45517 | E7: 140 | F7: 735 | G7: 2024-S2 | H7: Sim | I7: 0 | M7: Pro | N7: monthly | O7: Pago | P7: Sim | Q7: Não | R7: Não | S7: 6–15 | T7: 31–90 dias | U7: HealthTech | V7: US | W7: organic
A8: S-dceac6 | B8: A-417d2f | C8: 45290 | E8: 367 | F8: 796 | G8: Até 2024-S1 | H8: Sim | I8: 0 | M8: Enterprise | N8: annual | O8: Pago | P8: Sim | Q8: Não | R8: Não | S8: 1–5 | T8: 91–180 dias | U8: Cybersecurity | V8: IN | W8: partner
A9: S-8cad7b | B9: A-5f2961 | C9: 45649 | E9: 8 | F9: 304 | G9: 2024-S2 | H9: Não | I9: 0 | M9: Basic | N9: annual | O9: Pago | P9: Sim | Q9: Não | R9: Não | S9: 16–40 | T9: 31–90 dias | U9: HealthTech | V9: US | W9: partner
A10: S-24796e | B10: A-cc8c8f | C10: 45623 | E10: 34 | F10: 4577 | G10: 2024-S2 | H10: Sim | I10: 0 | M10: Enterprise | N10: annual | O10: Pago | P10: Não | Q10: Não | R10: Não | S10: 16–40 | T10: 91–180 dias | U10: DevTools | V10: US | W10: ads
A11: S-d0c344 | B11: A-80eeb6 | C11: 45592 | E11: 65 | F11: 1078 | G11: 2024-S2 | H11: Sim | I11: 0 | M11: Pro | N11: annual | O11: Pago | P11: Não | Q11: Não | R11: Não | S11: 16–40 | T11: Mais de 365 dias | U11: Cybersecurity | V11: UK | W11: organic
A12: S-477506 | B12: A-f03140 | C12: 45328 | E12: 329 | F12: 1323 | G12: Até 2024-S1 | H12: Sim | I12: 0 | M12: Pro | N12: annual | O12: Pago | P12: Sim | Q12: Não | R12: Não | S12: 16–40 | T12: 31–90 dias | U12: DevTools | V12: IN | W12: event
A13: S-79a9e1 | B13: A-3a5ad8 | C13: 45651 | E13: 6 | F13: 0 | G13: 2024-S2 | H13: Não | I13: 0 | M13: Enterprise | N13: annual | O13: Trial | P13: Sim | Q13: Não | R13: Não | S13: 16–40 | T13: Mais de 365 dias | U13: HealthTech | V13: US | W13: organic
A14: S-59dc4b | B14: A-f17767 | C14: 45186 | E14: 471 | F14: 1274 | G14: Até 2024-S1 | H14: Sim | I14: 0 | M14: Pro | N14: monthly | O14: Pago | P14: Sim | Q14: Sim | R14: Sim | S14: 16–40 | T14: 181–365 dias | U14: DevTools | V14: US | W14: event
A15: S-7acd8b | B15: A-7920cc | C15: 45490 | E15: 167 | F15: 741 | G15: 2024-S2 | H15: Sim | I15: 0 | M15: Basic | N15: annual | O15: Pago | P15: Sim | Q15: Não | R15: Não | S15: 16–40 | T15: 181–365 dias | U15: Cybersecurity | V15: FR | W15: ads
A16: S-428e9a | B16: A-8ae3fc | C16: 45577 | E16: 80 | F16: 0 | G16: 2024-S2 | H16: Sim | I16: 0 | M16: Enterprise | N16: monthly | O16: Trial | P16: Sim | Q16: Não | R16: Não | S16: 41+ | T16: 91–180 dias | U16: DevTools | V16: CA | W16: ads
A17: S-486088 | B17: A-0cc442 | C17: 45553 | E17: 104 | F17: 2205 | G17: 2024-S2 | H17: Sim | I17: 0 | M17: Pro | N17: monthly | O17: Pago | P17: Sim | Q17: Não | R17: Não | S17: 41+ | T17: 31–90 dias | U17: EdTech | V17: US | W17: organic
A18: S-13939b | B18: A-86902e | C18: 45128 | D18: 45507 | E18: 379 | F18: 0 | G18: Até 2024-S1 | H18: Sim | I18: 0 | J18: 45505 | K18: 3 | L18: Não | M18: Pro | N18: monthly | O18: Trial | P18: Sim | Q18: Não | R18: Não | S18: 16–40 | T18: 31–90 dias | U18: HealthTech | V18: IN | W18: other
A19: S-9333c5 | B19: A-ef84cf | C19: 45449 | D19: 45517 | E19: 68 | F19: 152 | G19: Até 2024-S1 | H19: Sim | I19: 0 | J19: 45505 | K19: 13 | L19: Não | M19: Basic | N19: annual | O19: Pago | P19: Não | Q19: Não | R19: Não | S19: 6–15 | T19: 91–180 dias | U19: EdTech | V19: US | W19: partner
A20: S-37e3ad | B20: A-b30291 | C20: 45407 | E20: 250 | F20: 95 | G20: Até 2024-S1 | H20: Sim | I20: 0 | M20: Basic | N20: monthly | O20: Pago | P20: Sim | Q20: Não | R20: Não | S20: 1–5 | T20: Conta nova (≤ 30 dias) | U20: HealthTech | V20: US | W20: event
A21: S-b17d04 | B21: A-e19ff6 | C21: 45357 | E21: 300 | F21: 392 | G21: Até 2024-S1 | H21: Sim | I21: 0 | M21: Pro | N21: monthly | O21: Pago | P21: Sim | Q21: Não | R21: Não | S21: 6–15 | T21: 181–365 dias | U21: Cybersecurity | V21: UK | W21: partner
A22: S-c27134 | B22: A-dec005 | C22: 45382 | E22: 275 | F22: 0 | G22: Até 2024-S1 | H22: Sim | I22: 0 | M22: Pro | N22: monthly | O22: Trial | P22: Sim | Q22: Não | R22: Não | S22: 16–40 | T22: 91–180 dias | U22: HealthTech | V22: US | W22: partner
A23: S-3bd427 | B23: A-2e3bad | C23: 45630 | D23: 45653 | E23: 23 | F23: 1159 | G23: 2024-S2 | H23: Não | I23: 1 | J23: 45627 | K23: 27 | L23: Não | M23: Basic | N23: monthly | O23: Pago | P23: Sim | Q23: Não | R23: Não | S23: 41+ | T23: Mais de 365 dias | U23: FinTech | V23: CA | W23: other
A24: S-82989b | B24: A-f5641b | C24: 45626 | E24: 31 | F24: 589 | G24: 2024-S2 | H24: Sim | I24: 0 | M24: Basic | N24: monthly | O24: Pago | P24: Sim | Q24: Não | R24: Não | S24: 16–40 | T24: 181–365 dias | U24: EdTech | V24: US | W24: other
A25: S-082b15 | B25: A-aa9511 | C25: 45331 | E25: 326 | F25: 19303 | G25: Até 2024-S1 | H25: Sim | I25: 0 | M25: Enterprise | N25: annual | O25: Pago | P25: Sim | Q25: Não | R25: Não | S25: 41+ | T25: 91–180 dias | U25: DevTools | V25: US | W25: other
A26: S-434140 | B26: A-075038 | C26: 45347 | E26: 310 | F26: 833 | G26: Até 2024-S1 | H26: Sim | I26: 0 | M26: Pro | N26: annual | O26: Pago | P26: Sim | Q26: Não | R26: Não | S26: 16–40 | T26: 181–365 dias | U26: HealthTech | V26: UK | W26: ads
A27: S-c07ede | B27: A-cea1f0 | C27: 45572 | E27: 85 | F27: 392 | G27: 2024-S2 | H27: Sim | I27: 0 | M27: Pro | N27: annual | O27: Pago | P27: Não | Q27: Não | R27: Não | S27: 6–15 | T27: 181–365 dias | U27: FinTech | V27: US | W27: event
A28: S-287914 | B28: A-a1b80b | C28: 45519 | E28: 138 | F28: 784 | G28: 2024-S2 | H28: Sim | I28: 0 | M28: Pro | N28: annual | O28: Pago | P28: Sim | Q28: Não | R28: Não | S28: 16–40 | T28: 181–365 dias | U28: HealthTech | V28: US | W28: organic
A29: S-b3bd43 | B29: A-b2225d | C29: 45599 | E29: 58 | F29: 2450 | G29: 2024-S2 | H29: Sim | I29: 0 | M29: Pro | N29: monthly | O29: Pago | P29: Não | Q29: Não | R29: Não | S29: 41+ | T29: 181–365 dias | U29: FinTech | V29: US | W29: ads
A30: S-4c82da | B30: A-b9eed8 | C30: 45505 | E30: 152 | F30: 539 | G30: 2024-S2 | H30: Sim | I30: 0 | M30: Pro | N30: monthly | O30: Pago | P30: Não | Q30: Não | R30: Não | S30: 6–15 | T30: 91–180 dias | U30: Cybersecurity | V30: US | W30: organic
A31: S-c75159 | B31: A-bcf87c | C31: 45526 | D31: 45563 | E31: 37 | F31: 6169 | G31: 2024-S2 | H31: Sim | I31: 0 | J31: 45536 | K31: 28 | L31: Sim | M31: Enterprise | N31: monthly | O31: Pago | P31: Sim | Q31: Não | R31: Não | S31: 16–40 | T31: 31–90 dias | U31: FinTech | V31: US | W31: event
A32: S-b5643b | B32: A-9f9299 | C32: 45454 | E32: 203 | F32: 5572 | G32: Até 2024-S1 | H32: Sim | I32: 0 | M32: Enterprise | N32: annual | O32: Pago | P32: Não | Q32: Não | R32: Não | S32: 16–40 | T32: 181–365 dias | U32: FinTech | V32: US | W32: organic
A33: S-49a9aa | B33: A-10b8f2 | C33: 45093 | E33: 564 | F33: 969 | G33: Até 2024-S1 | H33: Sim | I33: 0 | M33: Basic | N33: annual | O33: Pago | P33: Sim | Q33: Não | R33: Não | S33: 41+ | T33: 91–180 dias | U33: HealthTech | V33: DE | W33: organic
A34: S-2877e6 | B34: A-95b24a | C34: 45471 | E34: 186 | F34: 0 | G34: Até 2024-S1 | H34: Sim | I34: 0 | M34: Enterprise | N34: monthly | O34: Trial | P34: Sim | Q34: Sim | R34: Sim | S34: 16–40 | T34: Mais de 365 dias | U34: FinTech | V34: US | W34: event
A35: S-8c10c1 | B35: A-0651a4 | C35: 45651 | E35: 6 | F35: 12935 | G35: 2024-S2 | H35: Não | I35: 0 | M35: Enterprise | N35: annual | O35: Pago | P35: Sim | Q35: Não | R35: Não | S35: 41+ | T35: 31–90 dias | U35: HealthTech | V35: FR | W35: organic
A36: S-d7d398 | B36: A-fb186e | C36: 45654 | E36: 3 | F36: 0 | G36: 2024-S2 | H36: Não | I36: 0 | M36: Enterprise | N36: annual | O36: Trial | P36: Sim | Q36: Não | R36: Não | S36: 16–40 | T36: 31–90 dias | U36: EdTech | V36: IN | W36: organic
A37: S-ddad91 | B37: A-40906c | C37: 45464 | E37: 193 | F37: 0 | G37: Até 2024-S1 | H37: Sim | I37: 0 | M37: Enterprise | N37: annual | O37: Trial | P37: Não | Q37: Não | R37: Não | S37: 41+ | T37: 31–90 dias | U37: EdTech | V37: US | W37: ads
A38: S-6762fa | B38: A-40a557 | C38: 45334 | E38: 323 | F38: 3184 | G38: Até 2024-S1 | H38: Sim | I38: 0 | M38: Enterprise | N38: annual | O38: Pago | P38: Sim | Q38: Não | R38: Não | S38: 16–40 | T38: 31–90 dias | U38: Cybersecurity | V38: AU | W38: partner
A39: S-bb1cf1 | B39: A-3a5ad8 | C39: 45542 | E39: 115 | F39: 0 | G39: 2024-S2 | H39: Sim | I39: 0 | M39: Enterprise | N39: monthly | O39: Trial | P39: Não | Q39: Sim | R39: Não | S39: 6–15 | T39: 181–365 dias | U39: HealthTech | V39: US | W39: organic
A40: S-a805a5 | B40: A-2789e3 | C40: 45553 | E40: 104 | F40: 627 | G40: 2024-S2 | H40: Sim | I40: 0 | M40: Basic | N40: monthly | O40: Pago | P40: Sim | Q40: Não | R40: Não | S40: 16–40 | T40: Conta nova (≤ 30 dias) | U40: FinTech | V40: US | W40: partner
A41: S-da0a69 | B41: A-49b828 | C41: 45057 | E41: 600 | F41: 294 | G41: Até 2024-S1 | H41: Sim | I41: 0 | M41: Pro | N41: monthly | O41: Pago | P41: Sim | Q41: Não | R41: Não | S41: 6–15 | T41: Conta nova (≤ 30 dias) | U41: FinTech | V41: IN | W41: ads
A42: S-59c5d7 | B42: A-c16b88 | C42: 45584 | E42: 73 | F42: 665 | G42: 2024-S2 | H42: Sim | I42: 0 | M42: Basic | N42: monthly | O42: Pago | P42: Sim | Q42: Sim | R42: Não | S42: 16–40 | T42: 181–365 dias | U42: HealthTech | V42: US | W42: event
A43: S-d3faae | B43: A-5c9849 | C43: 45608 | E43: 49 | F43: 361 | G43: 2024-S2 | H43: Sim | I43: 0 | M43: Basic | N43: monthly | O43: Pago | P43: Sim | Q43: Não | R43: Não | S43: 16–40 | T43: Conta nova (≤ 30 dias) | U43: EdTech | V43: IN | W43: partner
... A53: S-36f6ec | B53: A-ccb686 | C53: 45520 | E53: 137 | F53: 1029 | G53: 2024-S2 | H53: Sim | I53: 0 | M53: Pro | N53: monthly | O53: Pago | P53: Sim | Q53: Sim | R53: Não | S53: 16–40 | T53: 181–365 dias | U53: DevTools | V53: US | W53: other
A54: S-aff55c | B54: A-bb2f49 | C54: 45305 | D54: 45655 | E54: 350 | F54: 0 | G54: Até 2024-S1 | H54: Sim | I54: 0 | J54: 45627 | K54: 29 | L54: Sim | M54: Pro | N54: monthly | O54: Trial | P54: Sim | Q54: Não | R54: Não | S54: 6–15 | T54: 181–365 dias | U54: Cybersecurity | V54: US | W54: other
A55: S-b9fc6c | B55: A-2ebb4b | C55: 45093 | E55: 564 | F55: 779 | G55: Até 2024-S1 | H55: Sim | I55: 0 | M55: Basic | N55: annual | O55: Pago | P55: Sim | Q55: Não | R55: Não | S55: 41+ | T55: 31–90 dias | U55: HealthTech | V55: US | W55: ads
A56: S-7f8cd8 | B56: A-53f4e3 | C56: 45553 | D56: 45613 | E56: 60 | F56: 3980 | G56: 2024-S2 | H56: Sim | I56: 0 | J56: 45597 | K56: 17 | L56: Não | M56: Enterprise | N56: monthly | O56: Pago | P56: Sim | Q56: Não | R56: Não | S56: 16–40 | T56: 91–180 dias | U56: Cybersecurity | V56: UK | W56: event
A57: S-e912e6 | B57: A-a8d89d | C57: 45272 | E57: 385 | F57: 15522 | G57: Até 2024-S1 | H57: Sim | I57: 0 | M57: Enterprise | N57: monthly | O57: Pago | P57: Sim | Q57: Não | R57: Não | S57: 41+ | T57: Conta nova (≤ 30 dias) | U57: EdTech | V57: US | W57: ads
A58: S-fef85a | B58: A-7f8241 | C58: 45510 | E58: 147 | F58: 1666 | G58: 2024-S2 | H58: Sim | I58: 0 | M58: Pro | N58: annual | O58: Pago | P58: Sim | Q58: Não | R58: Não | S58: 16–40 | T58: Mais de 365 dias | U58: EdTech | V58: US | W58: organic
A59: S-36d5c9 | B59: A-54ecc2 | C59: 45185 | E59: 472 | F59: 2189 | G59: Até 2024-S1 | H59: Sim | I59: 0 | M59: Enterprise | N59: monthly | O59: Pago | P59: Sim | Q59: Não | R59: Não | S59: 6–15 | T59: 91–180 dias | U59: Cybersecurity | V59: US | W59: partner
A60: S-b9ff15 | B60: A-95b24a | C60: 45299 | E60: 358 | F60: 8557 | G60: Até 2024-S1 | H60: Sim | I60: 0 | M60: Enterprise | N60: annual | O60: Pago | P60: Não | Q60: Não | R60: Não | S60: 41+ | T60: 181–365 dias | U60: FinTech | V60: US | W60: event
A61: S-10bd09 | B61: A-bbc346 | C61: 45538 | E61: 119 | F61: 950 | G61: 2024-S2 | H61: Sim | I61: 0 | M61: Basic | N61: annual | O61: Pago | P61: Sim | Q61: Não | R61: Não | S61: 41+ | T61: Conta nova (≤ 30 dias) | U61: FinTech | V61: US | W61: partner
A62: S-12bfc8 | B62: A-31ab9a | C62: 45632 | E62: 25 | F62: 5771 | G62: 2024-S2 | H62: Não | I62: 0 | M62: Enterprise | N62: monthly | O62: Pago | P62: Não | Q62: Não | R62: Não | S62: 16–40 | T62: 181–365 dias | U62: FinTech | V62: DE | W62: organic
A63: S-f5c472 | B63: A-faa28c | C63: 45482 | E63: 175 | F63: 912 | G63: 2024-S2 | H63: Sim | I63: 0 | M63: Basic | N63: monthly | O63: Pago | P63: Sim | Q63: Não | R63: Não | S63: 41+ | T63: 91–180 dias | U63: HealthTech | V63: US | W63: organic
A64: S-dbc1ca | B64: A-8adedc | C64: 45406 | E64: 251 | F64: 2786 | G64: Até 2024-S1 | H64: Sim | I64: 0 | M64: Enterprise | N64: annual | O64: Pago | P64: Sim | Q64: Não | R64: Não | S64: 6–15 | T64: 31–90 dias | U64: EdTech | V64: US | W64: event
A65: S-dc6dfd | B65: A-e08cd3 | C65: 45565 | E65: 92 | F65: 3283 | G65: 2024-S2 | H65: Sim | I65: 0 | M65: Pro | N65: monthly | O65: Pago | P65: Sim | Q65: Não | R65: Não | S65: 41+ | T65: Conta nova (≤ 30 dias) | U65: FinTech | V65: US | W65: ads
A66: S-b2d472 | B66: A-bcf87c | C66: 45531 | D66: 45637 | E66: 106 | F66: 1990 | G66: 2024-S2 | H66: Sim | I66: 0 | J66: 45627 | K66: 11 | L66: Não | M66: Enterprise | N66: annual | O66: Pago | P66: Não | Q66: Não | R66: Não | S66: 6–15 | T66: 31–90 dias | U66: FinTech | V66: US | W66: event
A67: S-9dfce0 | B67: A-e6afc1 | C67: 45534 | E67: 123 | F67: 98 | G67: 2024-S2 | H67: Sim | I67: 0 | M67: Pro | N67: annual | O67: Pago | P67: Sim | Q67: Não | R67: Não | S67: 1–5 | T67: Mais de 365 dias | U67: DevTools | V67: US | W67: ads
A68: S-9cb6a7 | B68: A-7f29a7 | C68: 45647 | E68: 10 | F68: 779 | G68: 2024-S2 | H68: Não | I68: 0 | M68: Basic | N68: monthly | O68: Pago | P68: Sim | Q68: Não | R68: Não | S68: 41+ | T68: 91–180 dias | U68: Cybersecurity | V68: UK | W68: event
A69: S-dabcd2 | B69: A-3ce5b8 | C69: 45557 | E69: 100 | F69: 0 | G69: 2024-S2 | H69: Sim | I69: 0 | M69: Pro | N69: monthly | O69: Trial | P69: Sim | Q69: Não | R69: Não | S69: 16–40 | T69: Mais de 365 dias | U69: FinTech | V69: IN | W69: ads
A70: S-8c3cc8 | B70: A-b2225d | C70: 45582 | E70: 75 | F70: 0 | G70: 2024-S2 | H70: Sim | I70: 0 | M70: Basic | N70: monthly | O70: Trial | P70: Sim | Q70: Não | R70: Não | S70: 41+ | T70: 181–365 dias | U70: FinTech | V70: US | W70: ads
A71: S-2923fc | B71: A-fa3095 | C71: 45481 | E71: 176 | F71: 13930 | G71: 2024-S2 | H71: Sim | I71: 0 | M71: Enterprise | N71: annual | O71: Pago | P71: Sim | Q71: Não | R71: Não | S71: 41+ | T71: 181–365 dias | U71: FinTech | V71: US | W71: ads
A72: S-f0a2e5 | B72: A-55f257 | C72: 45448 | E72: 209 | F72: 0 | G72: Até 2024-S1 | H72: Sim | I72: 0 | M72: Basic | N72: annual | O72: Trial | P72: Sim | Q72: Não | R72: Não | S72: 16–40 | T72: 91–180 dias | U72: FinTech | V72: US | W72: organic
A73: S-025bea | B73: A-9affe6 | C73: 45468 | E73: 189 | F73: 833 | G73: Até 2024-S1 | H73: Sim | I73: 0 | M73: Pro | N73: monthly | O73: Pago | P73: Sim | Q73: Sim | R73: Não | S73: 16–40 | T73: Mais de 365 dias | U73: Cybersecurity | V73: US | W73: other
A74: S-0e499f | B74: A-296d7c | C74: 45521 | E74: 136 | F74: 784 | G74: 2024-S2 | H74: Sim | I74: 0 | M74: Pro | N74: annual | O74: Pago | P74: Não | Q74: Não | R74: Não | S74: 16–40 | T74: 181–365 dias | U74: DevTools | V74: DE | W74: other
A75: S-0267b7 | B75: A-65a46c | C75: 45582 | D75: 45630 | E75: 48 | F75: 0 | G75: 2024-S2 | H75: Sim | I75: 0 | J75: 45627 | K75: 4 | L75: Não | M75: Enterprise | N75: monthly | O75: Trial | P75: Sim | Q75: Não | R75: Não | S75: 6–15 | T75: 181–365 dias | U75: HealthTech | V75: US | W75: event
A76: S-b5b9a5 | B76: A-812c5b | C76: 45498 | E76: 159 | F76: 1045 | G76: 2024-S2 | H76: Sim | I76: 0 | M76: Basic | N76: monthly | O76: Pago | P76: Sim | Q76: Não | R76: Não | S76: 41+ | T76: 91–180 dias | U76: DevTools | V76: CA | W76: organic
A77: S-8e45ba | B77: A-7f8241 | C77: 45273 | E77: 384 | F77: 646 | G77: Até 2024-S1 | H77: Sim | I77: 0 | M77: Basic | N77: annual | O77: Pago | P77: Não | Q77: Não | R77: Não | S77: 16–40 | T77: 181–365 dias | U77: EdTech | V77: US | W77: organic
A78: S-37ed34 | B78: A-d4ac0e | C78: 45480 | E78: 177 | F78: 3980 | G78: 2024-S2 | H78: Sim | I78: 0 | M78: Enterprise | N78: annual | O78: Pago | P78: Sim | Q78: Não | R78: Não | S78: 16–40 | T78: 31–90 dias | U78: DevTools | V78: UK | W78: ads
A79: S-65dbf3 | B79: A-17939a | C79: 45654 | E79: 3 | F79: 684 | G79: 2024-S2 | H79: Não | I79: 0 | M79: Basic | N79: monthly | O79: Pago | P79: Sim | Q79: Não | R79: Não | S79: 16–40 | T79: Conta nova (≤ 30 dias) | U79: HealthTech | V79: US | W79: organic
A80: S-ce5450 | B80: A-0a282f | C80: 45651 | D80: 45654 | E80: 3 | F80: 0 | G80: 2024-S2 | H80: Não | I80: 1 | J80: 45627 | K80: 28 | L80: Não | M80: Pro | N80: annual | O80: Trial | P80: Sim | Q80: Não | R80: Não | S80: 6–15 | T80: 91–180 dias | U80: DevTools | V80: US | W80: organic
A81: S-6c969d | B81: A-855a48 | C81: 45420 | E81: 237 | F81: 266 | G81: Até 2024-S1 | H81: Sim | I81: 0 | M81: Basic | N81: monthly | O81: Pago | P81: Não | Q81: Não | R81: Não | S81: 6–15 | T81: 91–180 dias | U81: EdTech | V81: US | W81: partner
A82: S-522aef | B82: A-f3ff05 | C82: 45526 | E82: 131 | F82: 196 | G82: 2024-S2 | H82: Sim | I82: 0 | M82: Pro | N82: annual | O82: Pago | P82: Sim | Q82: Não | R82: Não | S82: 1–5 | T82: 31–90 dias | U82: FinTech | V82: IN | W82: other
A83: S-82db05 | B83: A-417d2f | C83: 45635 | E83: 22 | F83: 1274 | G83: 2024-S2 | H83: Não | I83: 0 | M83: Pro | N83: monthly | O83: Pago | P83: Sim | Q83: Não | R83: Não | S83: 16–40 | T83: Mais de 365 dias | U83: Cybersecurity | V83: IN | W83: partner
A84: S-162596 | B84: A-462d45 | C84: 45351 | E84: 306 | F84: 0 | G84: Até 2024-S1 | H84: Sim | I84: 0 | M84: Pro | N84: monthly | O84: Trial | P84: Sim | Q84: Não | R84: Não | S84: 16–40 | T84: 31–90 dias | U84: Cybersecurity | V84: US | W84: partner
A85: S-f703bd | B85: A-202b67 | C85: 45539 | E85: 118 | F85: 539 | G85: 2024-S2 | H85: Sim | I85: 0 | M85: Pro | N85: monthly | O85: Pago | P85: Sim | Q85: Não | R85: Não | S85: 6–15 | T85: 91–180 dias | U85: HealthTech | V85: US | W85: organic
A86: S-a1d6ad | B86: A-eafc6e | C86: 45536 | E86: 121 | F86: 1323 | G86: 2024-S2 | H86: Sim | I86: 0 | M86: Pro | N86: monthly | O86: Pago | P86: Sim | Q86: Não | R86: Não | S86: 16–40 | T86: Mais de 365 dias | U86: DevTools | V86: US | W86: partner
A87: S-8b1fc1 | B87: A-309e54 | C87: 45652 | E87: 5 | F87: 0 | G87: 2024-S2 | H87: Não | I87: 0 | M87: Basic | N87: monthly | O87: Trial | P87: Sim | Q87: Não | R87: Não | S87: 6–15 | T87: Conta nova (≤ 30 dias) | U87: DevTools | V87: US | W87: other
A88: S-09cdac | B88: A-82861f | C88: 45504 | D88: 45539 | E88: 35 | F88: 779 | G88: 2024-S2 | H88: Sim | I88: 0 | J88: 45536 | K88: 4 | L88: Não | M88: Basic | N88: annual | O88: Pago | P88: Sim | Q88: Não | R88: Não | S88: 41+ | T88: 91–180 dias | U88: DevTools | V88: UK | W88: organic
A89: S-fa5301 | B89: A-ba6516 | C89: 45365 | E89: 292 | F89: 0 | G89: Até 2024-S1 | H89: Sim | I89: 0 | M89: Pro | N89: monthly | O89: Trial | P89: Não | Q89: Não | R89: Não | S89: 41+ | T89: 91–180 dias | U89: FinTech | V89: US | W89: ads
A90: S-69937b | B90: A-08e34e | C90: 45512 | E90: 145 | F90: 686 | G90: 2024-S2 | H90: Sim | I90: 0 | M90: Pro | N90: annual | O90: Pago | P90: Não | Q90: Não | R90: Não | S90: 6–15 | T90: 31–90 dias | U90: EdTech | V90: US | W90: event
A91: S-f2537d | B91: A-e43bf7 | C91: 45315 | E91: 342 | F91: 2156 | G91: Até 2024-S1 | H91: Sim | I91: 0 | M91: Pro | N91: monthly | O91: Pago | P91: Sim | Q91: Não | R91: Não | S91: 41+ | T91: 181–365 dias | U91: Cybersecurity | V91: AU | W91: other
A92: S-27f7b2 | B92: A-a1b80b | C92: 45385 | E92: 272 | F92: 722 | G92: Até 2024-S1 | H92: Sim | I92: 0 | M92: Basic | N92: annual | O92: Pago | P92: Sim | Q92: Não | R92: Não | S92: 16–40 | T92: 91–180 dias | U92: HealthTech | V92: US | W92: organic
A93: S-9c2b8e | B93: A-443f6f | C93: 45652 | E93: 5 | F93: 361 | G93: 2024-S2 | H93: Não | I93: 0 | M93: Basic | N93: annual | O93: Pago | P93: Sim | Q93: Sim | R93: Não | S93: 16–40 | T93: Conta nova (≤ 30 dias) | U93: Cybersecurity | V93: US | W93: organic
A94: S-a4f26d | B94: A-32728c | C94: 45067 | E94: 590 | F94: 980 | G94: Até 2024-S1 | H94: Sim | I94: 0 | M94: Pro | N94: monthly | O94: Pago | P94: Sim | Q94: Não | R94: Não | S94: 16–40 | T94: 91–180 dias | U94: DevTools | V94: US | W94: event
A95: S-0cb6ed | B95: A-ac85cd | C95: 45605 | D95: 45644 | E95: 39 | F95: 2597 | G95: 2024-S2 | H95: Sim | I95: 0 | J95: 45627 | K95: 18 | L95: Não | M95: Pro | N95: annual | O95: Pago | P95: Sim | Q95: Não | R95: Não | S95: 41+ | T95: 91–180 dias | U95: EdTech | V95: US | W95: partner
A96: S-367dee | B96: A-e19ff6 | C96: 45472 | E96: 185 | F96: 49 | G96: Até 2024-S1 | H96: Sim | I96: 0 | M96: Pro | N96: annual | O96: Pago | P96: Sim | Q96: Não | R96: Não | S96: 1–5 | T96: 181–365 dias | U96: Cybersecurity | V96: UK | W96: partner
A97: S-3b9ad8 | B97: A-6e08f3 | C97: 45650 | E97: 7 | F97: 5572 | G97: 2024-S2 | H97: Não | I97: 0 | M97: Enterprise | N97: monthly | O97: Pago | P97: Não | Q97: Não | R97: Não | S97: 16–40 | T97: Mais de 365 dias | U97: Cybersecurity | V97: US | W97: event
A98: S-c9f8c1 | B98: A-544d0a | C98: 45496 | E98: 161 | F98: 995 | G98: 2024-S2 | H98: Sim | I98: 0 | M98: Enterprise | N98: monthly | O98: Pago | P98: Sim | Q98: Não | R98: Sim | S98: 1–5 | T98: 31–90 dias | U98: DevTools | V98: US | W98: organic
A99: S-57cd05 | B99: A-8b0451 | C99: 45591 | E99: 66 | F99: 779 | G99: 2024-S2 | H99: Sim | I99: 0 | M99: Basic | N99: annual | O99: Pago | P99: Sim | Q99: Não | R99: Não | S99: 41+ | T99: 31–90 dias | U99: FinTech | V99: UK | W99: event
A100: S-e505c1 | B100: A-8ae3fc | C100: 45552 | E100: 105 | F100: 1666 | G100: 2024-S2 | H100: Sim | I100: 0 | M100: Pro | N100: annual | O100: Pago | P100: Sim | Q100: Não | R100: Não | S100: 16–40 | T100: 31–90 dias | U100: DevTools | V100: CA | W100: ads
A101: S-121b4d | B101: A-8ae3fc | C101: 45618 | E101: 39 | F101: 171 | G101: 2024-S2 | H101: Sim | I101: 0 | M101: Basic | N101: annual | O101: Pago | P101: Sim | Q101: Não | R101: Não | S101: 6–15 | T101: 91–180 dias | U101: DevTools | V101: CA | W101: ads
A102: S-72b4f2 | B102: A-4437e4 | C102: 45328 | E102: 329 | F102: 2401 | G102: Até 2024-S1 | H102: Sim | I102: 0 | M102: Pro | N102: annual | O102: Pago | P102: Sim | Q102: Não | R102: Não | S102: 41+ | T102: 91–180 dias | U102: Cybersecurity | V102: US | W102: event
A103: S-c9b0cc | B103: A-4d1e75 | C103: 45576 | E103: 81 | F103: 7562 | G103: 2024-S2 | H103: Sim | I103: 0 | M103: Enterprise | N103: monthly | O103: Pago | P103: Sim | Q103: Não | R103: Não | S103: 16–40 | T103: 31–90 dias | U103: DevTools | V103: US | W103: other
A104: S-27c993 | B104: A-098560 | C104: 45613 | E104: 44 | F104: 796 | G104: 2024-S2 | H104: Sim | I104: 0 | M104: Enterprise | N104: monthly | O104: Pago | P104: Sim | Q104: Não | R104: Não | S104: 1–5 | T104: Mais de 365 dias | U104: DevTools | V104: UK | W104: ads
A105: S-8b9889 | B105: A-ac9111 | C105: 45522 | E105: 135 | F105: 1029 | G105: 2024-S2 | H105: Sim | I105: 0 | M105: Pro | N105: monthly | O105: Pago | P105: Sim | Q105: Não | R105: Não | S105: 16–40 | T105: Mais de 365 dias | U105: HealthTech | V105: US | W105: event
A106: S-2214c6 | B106: A-3c1a3f | C106: 45572 | E106: 85 | F106: 4018 | G106: 2024-S2 | H106: Sim | I106: 0 | M106: Pro | N106: monthly | O106: Pago | P106: Sim | Q106: Não | R106: Não | S106: 41+ | T106: Mais de 365 dias | U106: DevTools | V106: UK | W106: event
A107: S-ce695e | B107: A-cb6cc6 | C107: 45437 | E107: 220 | F107: 0 | G107: Até 2024-S1 | H107: Sim | I107: 0 | M107: Enterprise | N107: annual | O107: Trial | P107: Não | Q107: Não | R107: Não | S107: 6–15 | T107: Mais de 365 dias | U107: DevTools | V107: US | W107: ads
... A121: S-feccd8 | B121: A-812c5b | C121: 45648 | E121: 9 | F121: 10945 | G121: 2024-S2 | H121: Não | I121: 0 | M121: Enterprise | N121: monthly | O121: Pago | P121: Sim | Q121: Não | R121: Não | S121: 41+ | T121: 181–365 dias | U121: DevTools | V121: CA | W121: organic
A122: S-0e4b0c | B122: A-39b19f | C122: 44985 | D122: 45092 | E122: 107 | F122: 1176 | G122: Até 2024-S1 | H122: Sim | I122: 0 | J122: 45078 | K122: 15 | L122: Não | M122: Pro | N122: annual | O122: Pago | P122: Sim | Q122: Não | R122: Sim | S122: 16–40 | T122: Conta nova (≤ 30 dias) | U122: FinTech | V122: US | W122: partner
...

Sheet Base_Contas
A1: account_id | B1: grupo | C1: industry | D1: referral_source | E1: churn_flag | F1: tem_evento | G1: tem_assin_encerrada | H1: mrr_ativo | I1: assinaturas | J1: pct_assin_2024S2 | K1: meses_de_casa | L1: seats | M1: uso_total | N1: erros_100_usos | O1: tickets | P1: satisfacao_media | Q1: teve_upgrade | R1: teve_downgrade | S1: is_devtools | T1: is_partner
A2: A-2e4581 | B2: Divergente | C2: EdTech | D2: partner | E2: FALSE | F2: TRUE | G2: FALSE | H2: 12603 | I2: 10 | J2: 1 | K2: 2.4969 | L2: 9 | M2: 535 | N2: 7.1028 | O2: 2 | P2: 3 | Q2: 1 | R2: 0 | S2: 0 | T2: 1
A3: A-43a9e3 | B3: Divergente | C3: FinTech | D3: other | E3: TRUE | F3: FALSE | G3: FALSE | H3: 10004 | I3: 8 | J3: 0.125 | K3: 16.4928 | L3: 18 | M3: 355 | N3: 3.9437 | O3: 3 | P3: 4 | Q3: 1 | R3: 0 | S3: 0 | T3: 0
A4: A-0a282f | B4: Divergente | C4: DevTools | D4: organic | E4: FALSE | F4: TRUE | G4: TRUE | H4: 13311 | I4: 15 | J4: 1 | K4: 4.1396 | L4: 1 | M4: 821 | N4: 5.8465 | O4: 3 | P4: 4.6667 | Q4: 1 | R4: 1 | S4: 1 | T4: 0
A5: A-1f0ac7 | B5: Divergente | C5: HealthTech | D5: other | E5: FALSE | F5: TRUE | G5: FALSE | H5: 9275 | I5: 7 | J5: 0.4286 | K5: 16.1643 | L5: 24 | M5: 382 | N5: 5.4974 | O5: 2 | Q5: 1 | R5: 0 | S5: 0 | T5: 0
A6: A-ce550d | B6: Churn (3 concordam) | C6: HealthTech | D6: event | E6: TRUE | F6: TRUE | G6: TRUE | H6: 25355 | I6: 9 | J6: 1 | K6: 2.1355 | L6: 35 | M6: 579 | N6: 5.3541 | O6: 7 | P6: 3.8 | Q6: 1 | R6: 0 | S6: 0 | T6: 0
A7: A-1b9609 | B7: Divergente | C7: EdTech | D7: ads | E7: FALSE | F7: TRUE | G7: TRUE | H7: 16614 | I7: 11 | J7: 0.3636 | K7: 14.653 | L7: 4 | M7: 457 | N7: 4.5952 | O7: 4 | P7: 3 | Q7: 0 | R7: 0 | S7: 0 | T7: 0
A8: A-a0ca4e | B8: Ativa (3 concordam) | C8: Cybersecurity | D8: ads | E8: FALSE | F8: FALSE | G8: FALSE | H8: 16633 | I8: 9 | J8: 0.6667 | K8: 9.7906 | L8: 11 | M8: 373 | N8: 3.7534 | O8: 6 | P8: 3.8 | Q8: 0 | R8: 0 | S8: 0 | T8: 0
A9: A-e5d6ab | B9: Divergente | C9: EdTech | D9: partner | E9: FALSE | F9: TRUE | G9: TRUE | H9: 12383 | I9: 10 | J9: 0.3 | K9: 20.5667 | L9: 3 | M9: 382 | N9: 6.0209 | O9: 3 | Q9: 0 | R9: 0 | S9: 0 | T9: 1
A10: A-7dacce | B10: Divergente | C10: Cybersecurity | D10: event | E10: TRUE | F10: TRUE | G10: FALSE | H10: 23057 | I10: 10 | J10: 1 | K10: 3.6797 | L10: 12 | M10: 472 | N10: 6.1441 | O10: 4 | P10: 3.6667 | Q10: 1 | R10: 0 | S10: 0 | T10: 0
A11: A-10b8da | B11: Divergente | C11: DevTools | D11: partner | E11: TRUE | F11: FALSE | G11: TRUE | H11: 5404 | I11: 6 | J11: 0.3333 | K11: 19.8111 | L11: 14 | M11: 257 | N11: 5.4475 | O11: 3 | P11: 3.5 | Q11: 1 | R11: 0 | S11: 1 | T11: 1
A12: A-592832 | B12: Churn (3 concordam) | C12: Cybersecurity | D12: organic | E12: TRUE | F12: TRUE | G12: TRUE | H12: 26833 | I12: 19 | J12: 1 | K12: 3.1869 | L12: 18 | M12: 1053 | N12: 5.2232 | O12: 3 | P12: 5 | Q12: 1 | R12: 1 | S12: 0 | T12: 0
A13: A-d40bf7 | B13: Ativa (3 concordam) | C13: FinTech | D13: organic | E13: FALSE | F13: FALSE | G13: FALSE | H13: 43247 | I13: 10 | J13: 1 | K13: 1.7413 | L13: 59 | M13: 562 | N13: 3.9146 | O13: 2 | P13: 5 | Q13: 1 | R13: 0 | S13: 0 | T13: 0
A14: A-6c093d | B14: Divergente | C14: DevTools | D14: partner | E14: FALSE | F14: FALSE | G14: TRUE | H14: 15556 | I14: 12 | J14: 0.4167 | K14: 20.5996 | L14: 7 | M14: 670 | N14: 4.4776 | O14: 3 | P14: 5 | Q14: 1 | R14: 0 | S14: 1 | T14: 1
A15: A-462d45 | B15: Divergente | C15: Cybersecurity | D15: partner | E15: FALSE | F15: TRUE | G15: TRUE | H15: 18752 | I15: 12 | J15: 0.3333 | K15: 11.5318 | L15: 11 | M15: 642 | N15: 4.0498 | O15: 4 | P15: 4 | Q15: 1 | R15: 1 | S15: 0 | T15: 1
A16: A-956988 | B16: Divergente | C16: EdTech | D16: ads | E16: FALSE | F16: TRUE | G16: TRUE | H16: 29407 | I16: 13 | J16: 1 | K16: 1.0185 | L16: 1 | M16: 658 | N16: 7.4468 | O16: 2 | P16: 3 | Q16: 0 | R16: 1 | S16: 0 | T16: 0
A17: A-ac14bb | B17: Divergente | C17: FinTech | D17: partner | E17: FALSE | F17: TRUE | G17: TRUE | H17: 20382 | I17: 8 | J17: 0.125 | K17: 15.77 | L17: 21 | M17: 531 | N17: 7.9096 | O17: 2 | P17: 4 | Q17: 1 | R17: 0 | S17: 0 | T17: 1
A18: A-463db0 | B18: Divergente | C18: HealthTech | D18: partner | E18: FALSE | F18: TRUE | G18: FALSE | H18: 13266 | I18: 7 | J18: 1 | K18: 0.8542 | L18: 15 | M18: 367 | N18: 3.5422 | O18: 6 | P18: 4.25 | Q18: 0 | R18: 0 | S18: 0 | T18: 1
A19: A-ce66f8 | B19: Ativa (3 concordam) | C19: EdTech | D19: event | E19: FALSE | F19: FALSE | G19: FALSE | H19: 11858 | I19: 6 | J19: 0.5 | K19: 16.2957 | L19: 29 | M19: 494 | N19: 3.8462 | O19: 6 | P19: 3.5 | Q19: 0 | R19: 0 | S19: 0 | T19: 0
A20: A-c4ea60 | B20: Divergente | C20: FinTech | D20: other | E20: TRUE | F20: FALSE | G20: FALSE | H20: 14646 | I20: 9 | J20: 0.6667 | K20: 21.7823 | L20: 18 | M20: 427 | N20: 4.2155 | O20: 5 | P20: 3.6 | Q20: 0 | R20: 1 | S20: 0 | T20: 0
A21: A-832ec2 | B21: Divergente | C21: FinTech | D21: event | E21: FALSE | F21: TRUE | G21: FALSE | H21: 9299 | I21: 8 | J21: 0.375 | K21: 13.4045 | L21: 4 | M21: 511 | N21: 4.8924 | O21: 3 | P21: 4 | Q21: 1 | R21: 0 | S21: 0 | T21: 0
... A25: A-30b4ca | B25: Divergente | C25: EdTech | D25: organic | E25: TRUE | F25: TRUE | G25: FALSE | H25: 75938 | I25: 8 | J25: 0.5 | K25: 7.3922 | L25: 86 | M25: 402 | N25: 5.4726 | O25: 3 | P25: 4 | Q25: 0 | R25: 0 | S25: 0 | T25: 0
A26: A-9f2731 | B26: Divergente | C26: FinTech | D26: event | E26: FALSE | F26: TRUE | G26: FALSE | H26: 3613 | I26: 7 | J26: 1 | K26: 2.8912 | L26: 1 | M26: 324 | N26: 6.1728 | O26: 0 | Q26: 0 | R26: 1 | S26: 0 | T26: 0
A27: A-32fb14 | B27: Churn (3 concordam) | C27: DevTools | D27: event | E27: TRUE | F27: TRUE | G27: TRUE | H27: 8775 | I27: 9 | J27: 0.3333 | K27: 21.848 | L27: 26 | M27: 488 | N27: 3.8934 | O27: 5 | P27: 4.5 | Q27: 1 | R27: 0 | S27: 1 | T27: 0
A28: A-00cac8 | B28: Ativa (3 concordam) | C28: HealthTech | D28: organic | E28: FALSE | F28: FALSE | G28: FALSE | H28: 14121 | I28: 9 | J28: 0.5556 | K28: 15.54 | L28: 8 | M28: 602 | N28: 5.1495 | O28: 2 | Q28: 0 | R28: 1 | S28: 0 | T28: 0
A29: A-35083d | B29: Divergente | C29: HealthTech | D29: partner | E29: TRUE | F29: FALSE | G29: TRUE | H29: 31502 | I29: 16 | J29: 0.4375 | K29: 20.1396 | L29: 19 | M29: 791 | N29: 4.6776 | O29: 4 | P29: 5 | Q29: 1 | R29: 0 | S29: 0 | T29: 1
A30: A-eb7fac | B30: Divergente | C30: DevTools | D30: organic | E30: FALSE | F30: TRUE | G30: TRUE | H30: 41753 | I30: 10 | J30: 0.5 | K30: 14.1273 | L30: 7 | M30: 538 | N30: 8.1784 | O30: 4 | P30: 4 | Q30: 0 | R30: 0 | S30: 1 | T30: 0
A31: A-b20d99 | B31: Divergente | C31: HealthTech | D31: other | E31: FALSE | F31: TRUE | G31: FALSE | H31: 11069 | I31: 7 | J31: 0.5714 | K31: 15.1458 | L31: 20 | M31: 329 | N31: 3.6474 | O31: 2 | P31: 3.5 | Q31: 1 | R31: 0 | S31: 0 | T31: 0
A32: A-396e5f | B32: Divergente | C32: Cybersecurity | D32: other | E32: FALSE | F32: TRUE | G32: FALSE | H32: 10236 | I32: 10 | J32: 1 | K32: 2.9569 | L32: 2 | M32: 540 | N32: 4.2593 | O32: 5 | P32: 4 | Q32: 1 | R32: 1 | S32: 0 | T32: 0
A33: A-45ce7a | B33: Divergente | C33: FinTech | D33: ads | E33: FALSE | F33: FALSE | G33: TRUE | H33: 7432 | I33: 7 | J33: 0.2857 | K33: 17.3142 | L33: 16 | M33: 424 | N33: 7.0755 | O33: 5 | P33: 3.6667 | Q33: 1 | R33: 1 | S33: 0 | T33: 0
A34: A-08e34e | B34: Divergente | C34: EdTech | D34: event | E34: TRUE | F34: TRUE | G34: FALSE | H34: 21821 | I34: 11 | J34: 1 | K34: 6.1437 | L34: 14 | M34: 651 | N34: 4.9155 | O34: 3 | P34: 3 | Q34: 0 | R34: 0 | S34: 0 | T34: 0
A35: A-8145a0 | B35: Divergente | C35: Cybersecurity | D35: partner | E35: FALSE | F35: TRUE | G35: TRUE | H35: 12285 | I35: 12 | J35: 0.25 | K35: 20.2382 | L35: 2 | M35: 693 | N35: 3.8961 | O35: 6 | P35: 4 | Q35: 1 | R35: 0 | S35: 0 | T35: 1
A36: A-bad8c1 | B36: Divergente | C36: FinTech | D36: organic | E36: FALSE | F36: TRUE | G36: FALSE | H36: 7797 | I36: 7 | J36: 0 | K36: 22.0452 | L36: 7 | M36: 385 | N36: 2.8571 | O36: 1 | P36: 4 | Q36: 1 | R36: 0 | S36: 0 | T36: 0
A37: A-44dc83 | B37: Divergente | C37: EdTech | D37: other | E37: FALSE | F37: TRUE | G37: FALSE | H37: 456 | I37: 4 | J37: 0.75 | K37: 7.655 | L37: 5 | M37: 248 | N37: 5.2419 | O37: 7 | P37: 4.6 | Q37: 0 | R37: 0 | S37: 0 | T37: 0
A38: A-f446b6 | B38: Divergente | C38: DevTools | D38: ads | E38: FALSE | F38: FALSE | G38: TRUE | H38: 8805 | I38: 9 | J38: 0.3333 | K38: 19.6797 | L38: 5 | M38: 376 | N38: 8.2447 | O38: 8 | P38: 4.25 | Q38: 0 | R38: 0 | S38: 1 | T38: 0
A39: A-a45270 | B39: Divergente | C39: HealthTech | D39: ads | E39: FALSE | F39: TRUE | G39: TRUE | H39: 19984 | I39: 12 | J39: 1 | K39: 6.2423 | L39: 3 | M39: 733 | N39: 7.2306 | O39: 4 | P39: 4 | Q39: 1 | R39: 1 | S39: 0 | T39: 0
A40: A-854864 | B40: Divergente | C40: FinTech | D40: event | E40: FALSE | F40: TRUE | G40: TRUE | H40: 14379 | I40: 6 | J40: 1 | K40: 0.7885 | L40: 20 | M40: 248 | N40: 4.0323 | O40: 5 | P40: 4.8 | Q40: 0 | R40: 0 | S40: 0 | T40: 0
... A57: A-4c38bc | B57: Divergente | C57: HealthTech | D57: event | E57: TRUE | F57: FALSE | G57: TRUE | H57: 45612 | I57: 16 | J57: 0.5 | K57: 9.7577 | L57: 36 | M57: 818 | N57: 3.3007 | O57: 3 | P57: 3.5 | Q57: 1 | R57: 0 | S57: 0 | T57: 0
A58: A-1b707d | B58: Divergente | C58: Cybersecurity | D58: organic | E58: FALSE | F58: TRUE | G58: TRUE | H58: 9180 | I58: 8 | J58: 0.375 | K58: 17.6099 | L58: 1 | M58: 399 | N58: 3.0075 | O58: 3 | Q58: 1 | R58: 0 | S58: 0 | T58: 0
A59: A-6f8ad2 | B59: Divergente | C59: EdTech | D59: organic | E59: FALSE | F59: FALSE | G59: TRUE | H59: 25046 | I59: 17 | J59: 1 | K59: 5.7495 | L59: 1 | M59: 924 | N59: 6.3853 | O59: 4 | P59: 4.3333 | Q59: 1 | R59: 1 | S59: 0 | T59: 0
A60: A-4d1e75 | B60: Divergente | C60: DevTools | D60: other | E60: FALSE | F60: TRUE | G60: FALSE | H60: 31390 | I60: 13 | J60: 1 | K60: 4.3368 | L60: 20 | M60: 477 | N60: 5.2411 | O60: 2 | P60: 4 | Q60: 1 | R60: 1 | S60: 1 | T60: 0
A61: A-9ee962 | B61: Churn (3 concordam) | C61: HealthTech | D61: ads | E61: TRUE | F61: TRUE | G61: TRUE | H61: 9249 | I61: 9 | J61: 0.1111 | K61: 22.078 | L61: 9 | M61: 439 | N61: 3.8724 | O61: 3 | P61: 4 | Q61: 1 | R61: 1 | S61: 0 | T61: 0
A62: A-378b99 | B62: Divergente | C62: EdTech | D62: ads | E62: FALSE | F62: TRUE | G62: TRUE | H62: 10524 | I62: 12 | J62: 1 | K62: 3.9754 | L62: 8 | M62: 565 | N62: 6.7257 | O62: 6 | P62: 4.5 | Q62: 1 | R62: 1 | S62: 0 | T62: 0
A63: A-94d3da | B63: Divergente | C63: HealthTech | D63: other | E63: FALSE | F63: TRUE | G63: TRUE | H63: 20664 | I63: 12 | J63: 0.25 | K63: 19.9754 | L63: 41 | M63: 464 | N63: 5.3879 | O63: 6 | P63: 3.5 | Q63: 1 | R63: 0 | S63: 0 | T63: 0
A64: A-e351e1 | B64: Divergente | C64: EdTech | D64: other | E64: FALSE | F64: TRUE | G64: TRUE | H64: 2871 | I64: 5 | J64: 1 | K64: 3.154 | L64: 33 | M64: 295 | N64: 7.4576 | O64: 4 | P64: 3.75 | Q64: 0 | R64: 0 | S64: 0 | T64: 0
A65: A-9badbd | B65: Divergente | C65: Cybersecurity | D65: ads | E65: FALSE | F65: FALSE | G65: TRUE | H65: 20299 | I65: 13 | J65: 0.9231 | K65: 6.4066 | L65: 5 | M65: 729 | N65: 6.1728 | O65: 5 | P65: 5 | Q65: 0 | R65: 0 | S65: 0 | T65: 0
A66: A-7e0a10 | B66: Divergente | C66: FinTech | D66: ads | E66: FALSE | F66: TRUE | G66: FALSE | H66: 41116 | I66: 10 | J66: 0.2 | K66: 13.4374 | L66: 46 | M66: 511 | N66: 6.8493 | O66: 5 | P66: 4 | Q66: 1 | R66: 0 | S66: 0 | T66: 0
A67: A-118d55 | B67: Divergente | C67: Cybersecurity | D67: organic | E67: FALSE | F67: TRUE | G67: TRUE | H67: 18148 | I67: 12 | J67: 1 | K67: 2.2998 | L67: 8 | M67: 599 | N67: 5.5092 | O67: 5 | P67: 4.3333 | Q67: 1 | R67: 1 | S67: 0 | T67: 0
A68: A-526d93 | B68: Divergente | C68: HealthTech | D68: organic | E68: FALSE | F68: TRUE | G68: TRUE | H68: 30644 | I68: 9 | J68: 0.6667 | K68: 8.5749 | L68: 43 | M68: 565 | N68: 7.9646 | O68: 5 | P68: 3.5 | Q68: 1 | R68: 0 | S68: 0 | T68: 0
A69: A-f92792 | B69: Divergente | C69: FinTech | D69: ads | E69: FALSE | F69: TRUE | G69: FALSE | H69: 18807 | I69: 14 | J69: 1 | K69: 5.9138 | L69: 1 | M69: 528 | N69: 5.8712 | O69: 2 | P69: 4 | Q69: 1 | R69: 1 | S69: 0 | T69: 0
A70: A-84ebe4 | B70: Churn (3 concordam) | C70: FinTech | D70: ads | E70: TRUE | F70: TRUE | G70: TRUE | H70: 27652 | I70: 11 | J70: 0.1818 | K70: 21.6838 | L70: 18 | M70: 396 | N70: 6.5657 | O70: 4 | P70: 4 | Q70: 0 | R70: 0 | S70: 0 | T70: 0
... A79: A-ee42db | B79: Divergente | C79: EdTech | D79: ads | E79: FALSE | F79: TRUE | G79: FALSE | H79: 11567 | I79: 12 | J79: 0.25 | K79: 20.2382 | L79: 13 | M79: 511 | N79: 6.4579 | O79: 4 | P79: 3 | Q79: 1 | R79: 1 | S79: 0 | T79: 0
A80: A-432483 | B80: Divergente | C80: Cybersecurity | D80: ads | E80: FALSE | F80: FALSE | G80: TRUE | H80: 22941 | I80: 9 | J80: 0.2222 | K80: 22.8008 | L80: 4 | M80: 451 | N80: 6.2084 | O80: 1 | Q80: 1 | R80: 0 | S80: 0 | T80: 0
A81: A-9208f0 | B81: Churn (3 concordam) | C81: EdTech | D81: organic | E81: TRUE | F81: TRUE | G81: TRUE | H81: 3413 | I81: 8 | J81: 0.125 | K81: 19.7125 | L81: 1 | M81: 538 | N81: 5.7621 | O81: 8 | P81: 3.3333 | Q81: 1 | R81: 0 | S81: 0 | T81: 0
A82: A-98a59a | B82: Divergente | C82: FinTech | D82: partner | E82: FALSE | F82: TRUE | G82: FALSE | H82: 36456 | I82: 10 | J82: 0.4 | K82: 16.9199 | L82: 56 | M82: 455 | N82: 4.6154 | O82: 3 | P82: 4.5 | Q82: 1 | R82: 1 | S82: 0 | T82: 1
A83: A-fe79a5 | B83: Divergente | C83: HealthTech | D83: ads | E83: FALSE | F83: FALSE | G83: TRUE | H83: 11741 | I83: 10 | J83: 0.5 | K83: 10.3162 | L83: 9 | M83: 335 | N83: 5.0746 | O83: 4 | P83: 5 | Q83: 1 | R83: 0 | S83: 0 | T83: 0
A84: A-726cfa | B84: Divergente | C84: DevTools | D84: partner | E84: FALSE | F84: TRUE | G84: TRUE | H84: 34243 | I84: 19 | J84: 0.3684 | K84: 18.037 | L84: 11 | M84: 993 | N84: 4.5317 | O84: 3 | P84: 4 | Q84: 1 | R84: 0 | S84: 1 | T84: 1
A85: A-c43359 | B85: Divergente | C85: FinTech | D85: organic | E85: FALSE | F85: TRUE | G85: TRUE | H85: 10868 | I85: 8 | J85: 1 | K85: 1.4784 | L85: 38 | M85: 461 | N85: 6.9414 | O85: 3 | P85: 4 | Q85: 1 | R85: 1 | S85: 0 | T85: 0
A86: A-271f46 | B86: Divergente | C86: DevTools | D86: event | E86: TRUE | F86: TRUE | G86: FALSE | H86: 19604 | I86: 8 | J86: 0.25 | K86: 22.7023 | L86: 38 | M86: 373 | N86: 4.2895 | O86: 1 | Q86: 0 | R86: 0 | S86: 1 | T86: 0
A87: A-157070 | B87: Divergente | C87: FinTech | D87: ads | E87: FALSE | F87: TRUE | G87: TRUE | H87: 22395 | I87: 16 | J87: 0.625 | K87: 13.7331 | L87: 16 | M87: 696 | N87: 3.7356 | O87: 3 | P87: 3 | Q87: 1 | R87: 1 | S87: 0 | T87: 0
A88: A-40a557 | B88: Divergente | C88: Cybersecurity | D88: partner | E88: FALSE | F88: TRUE | G88: TRUE | H88: 20140 | I88: 9 | J88: 0.4444 | K88: 12.9446 | L88: 16 | M88: 402 | N88: 4.2289 | O88: 7 | P88: 3.6667 | Q88: 1 | R88: 0 | S88: 0 | T88: 1
A89: A-66224b | B89: Divergente | C89: HealthTech | D89: other | E89: FALSE | F89: FALSE | G89: TRUE | H89: 50876 | I89: 12 | J89: 1 | K89: 2.4312 | L89: 92 | M89: 626 | N89: 4.6326 | O89: 6 | P89: 3.5 | Q89: 0 | R89: 0 | S89: 0 | T89: 0
A90: A-91e948 | B90: Ativa (3 concordam) | C90: EdTech | D90: partner | E90: FALSE | F90: FALSE | G90: FALSE | H90: 21894 | I90: 7 | J90: 0.2857 | K90: 23.0637 | L90: 41 | M90: 404 | N90: 3.9604 | O90: 0 | Q90: 1 | R90: 0 | S90: 0 | T90: 1
A91: A-104f1a | B91: Divergente | C91: Cybersecurity | D91: other | E91: FALSE | F91: TRUE | G91: TRUE | H91: 6590 | I91: 8 | J91: 1 | K91: 4.4682 | L91: 24 | M91: 438 | N91: 5.0228 | O91: 5 | P91: 3.75 | Q91: 0 | R91: 0 | S91: 0 | T91: 0
A92: A-7988d1 | B92: Divergente | C92: Cybersecurity | D92: other | E92: FALSE | F92: TRUE | G92: TRUE | H92: 10065 | I92: 9 | J92: 0.6667 | K92: 12.386 | L92: 33 | M92: 449 | N92: 6.2361 | O92: 3 | P92: 4.3333 | Q92: 0 | R92: 0 | S92: 0 | T92: 0
A93: A-faa28c | B93: Divergente | C93: HealthTech | D93: organic | E93: FALSE | F93: TRUE | G93: TRUE | H93: 39300 | I93: 14 | J93: 0.4286 | K93: 11.039 | L93: 48 | M93: 585 | N93: 4.1026 | O93: 4 | P93: 4.6667 | Q93: 1 | R93: 0 | S93: 0 | T93: 0
A94: A-f25509 | B94: Divergente | C94: EdTech | D94: other | E94: FALSE | F94: TRUE | G94: FALSE | H94: 16122 | I94: 5 | J94: 0.6 | K94: 9.3306 | L94: 32 | M94: 229 | N94: 6.5502 | O94: 6 | P94: 4.6667 | Q94: 0 | R94: 1 | S94: 0 | T94: 0
A95: A-3a7284 | B95: Divergente | C95: FinTech | D95: organic | E95: FALSE | F95: TRUE | G95: TRUE | H95: 32515 | I95: 12 | J95: 1 | K95: 1.4456 | L95: 31 | M95: 609 | N95: 4.9261 | O95: 3 | P95: 3.5 | Q95: 1 | R95: 1 | S95: 0 | T95: 0
A96: A-3a5ad8 | B96: Ativa (3 concordam) | C96: HealthTech | D96: organic | E96: FALSE | F96: FALSE | G96: FALSE | H96: 28701 | I96: 13 | J96: 0.3846 | K96: 12.8789 | L96: 9 | M96: 506 | N96: 4.5455 | O96: 4 | P96: 4.5 | Q96: 1 | R96: 1 | S96: 0 | T96: 0
A97: A-65a46c | B97: Divergente | C97: HealthTech | D97: event | E97: FALSE | F97: FALSE | G97: TRUE | H97: 22675 | I97: 8 | J97: 0.375 | K97: 13.8973 | L97: 1 | M97: 370 | N97: 5.6757 | O97: 8 | P97: 4 | Q97: 1 | R97: 0 | S97: 0 | T97: 0
A98: A-8b25f2 | B98: Divergente | C98: Cybersecurity | D98: ads | E98: TRUE | F98: FALSE | G98: TRUE | H98: 12965 | I98: 13 | J98: 0.6154 | K98: 10.4476 | L98: 6 | M98: 565 | N98: 3.5398 | O98: 2 | P98: 4 | Q98: 1 | R98: 1 | S98: 0 | T98: 0
A99: A-fabe19 | B99: Divergente | C99: DevTools | D99: ads | E99: FALSE | F99: FALSE | G99: TRUE | H99: 9552 | I99: 7 | J99: 1 | K99: 1.6427 | L99: 1 | M99: 337 | N99: 4.7478 | O99: 3 | P99: 4 | Q99: 1 | R99: 0 | S99: 1 | T99: 0
A100: A-adc1f3 | B100: Divergente | C100: Cybersecurity | D100: organic | E100: FALSE | F100: FALSE | G100: TRUE | H100: 16658 | I100: 9 | J100: 1 | K100: 4.8624 | L100: 2 | M100: 334 | N100: 7.7844 | O100: 3 | P100: 3.5 | Q100: 0 | R100: 0 | S100: 0 | T100: 0
A101: A-503d5a | B101: Divergente | C101: FinTech | D101: other | E101: TRUE | F101: FALSE | G101: FALSE | H101: 17884 | I101: 12 | J101: 0.25 | K101: 14.3573 | L101: 4 | M101: 605 | N101: 5.2893 | O101: 9 | P101: 4 | Q101: 0 | R101: 1 | S101: 0 | T101: 0
A102: A-fd7ad3 | B102: Divergente | C102: Cybersecurity | D102: event | E102: FALSE | F102: TRUE | G102: TRUE | H102: 904 | I102: 10 | J102: 1 | K102: 1.9713 | L102: 1 | M102: 567 | N102: 7.4074 | O102: 8 | P102: 4.1667 | Q102: 1 | R102: 0 | S102: 0 | T102: 0
... A108: A-22f2df | B108: Ativa (3 concordam) | C108: DevTools | D108: ads | E108: FALSE | F108: FALSE | G108: FALSE | H108: 7451 | I108: 9 | J108: 1 | K108: 0.5585 | L108: 3 | M108: 429 | N108: 3.9627 | O108: 5 | P108: 5 | Q108: 1 | R108: 1 | S108: 1 | T108: 0
A109: A-039727 | B109: Divergente | C109: EdTech | D109: organic | E109: FALSE | F109: TRUE | G109: TRUE | H109: 31445 | I109: 15 | J109: 1 | K109: 1.9384 | L109: 25 | M109: 768 | N109: 4.1667 | O109: 0 | Q109: 1 | R109: 1 | S109: 0 | T109: 0
A110: A-2e3bad | B110: Divergente | C110: FinTech | D110: other | E110: FALSE | F110: TRUE | G110: TRUE | H110: 41724 | I110: 10 | J110: 0.4 | K110: 16.6242 | L110: 61 | M110: 435 | N110: 5.977 | O110: 5 | P110: 3.5 | Q110: 0 | R110: 0 | S110: 0 | T110: 0
A111: A-484819 | B111: Divergente | C111: HealthTech | D111: organic | E111: FALSE | F111: TRUE | G111: TRUE | H111: 15088 | I111: 8 | J111: 0.25 | K111: 22.308 | L111: 18 | M111: 336 | N111: 5.9524 | O111: 5 | P111: 4.5 | Q111: 1 | R111: 0 | S111: 0 | T111: 0
A112: A-425e76 | B112: Churn (3 concordam) | C112: DevTools | D112: other | E112: TRUE | F112: TRUE | G112: TRUE | H112: 10743 | I112: 11 | J112: 0.2727 | K112: 19.5154 | L112: 8 | M112: 438 | N112: 5.4795 | O112: 5 | P112: 3.3333 | Q112: 1 | R112: 0 | S112: 1 | T112: 0
A113: A-e83938 | B113: Divergente | C113: DevTools | D113: other | E113: TRUE | F113: TRUE | G113: FALSE | H113: 7503 | I113: 8 | J113: 0.5 | K113: 13.3388 | L113: 2 | M113: 266 | N113: 6.7669 | O113: 4 | P113: 3 | Q113: 1 | R113: 0 | S113: 1 | T113: 0
A114: A-ad296b | B114: Divergente | C114: DevTools | D114: event | E114: FALSE | F114: FALSE | G114: TRUE | H114: 17708 | I114: 6 | J114: 1 | K114: 5.5524 | L114: 38 | M114: 294 | N114: 4.0816 | O114: 3 | P114: 3.6667 | Q114: 0 | R114: 0 | S114: 1 | T114: 0
A115: A-e51ec7 | B115: Divergente | C115: FinTech | D115: partner | E115: FALSE | F115: TRUE | G115: TRUE | H115: 24076 | I115: 8 | J115: 0.5 | K115: 15.2772 | L115: 2 | M115: 417 | N115: 4.3165 | O115: 3 | P115: 5 | Q115: 1 | R115: 1 | S115: 0 | T115: 1
A116: A-0aaf6e | B116: Divergente | C116: FinTech | D116: organic | E116: FALSE | F116: FALSE | G116: TRUE | H116: 23496 | I116: 9 | J116: 0.8889 | K116: 7.6879 | L116: 3 | M116: 599 | N116: 6.5109 | O116: 5 | P116: 4 | Q116: 0 | R116: 0 | S116: 0 | T116: 0
A117: A-e61e98 | B117: Divergente | C117: FinTech | D117: partner | E117: TRUE | F117: TRUE | G117: FALSE | H117: 13484 | I117: 9 | J117: 0.2222 | K117: 14.3901 | L117: 19 | M117: 527 | N117: 4.7438 | O117: 6 | P117: 4.6 | Q117: 1 | R117: 0 | S117: 0 | T117: 1
A118: A-92a333 | B118: Ativa (3 concordam) | C118: FinTech | D118: event | E118: FALSE | F118: FALSE | G118: FALSE | H118: 10659 | I118: 6 | J118: 0.3333 | K118: 21.2895 | L118: 9 | M118: 364 | N118: 8.2418 | O118: 4 | Q118: 0 | R118: 1 | S118: 0 | T118: 0
A119: A-95b24a | B119: Divergente | C119: FinTech | D119: event | E119: TRUE | F119: FALSE | G119: FALSE | H119: 25034 | I119: 11 | J119: 0.1818 | K119: 18.8583 | L119: 38 | M119: 611 | N119: 5.5646 | O119: 5 | P119: 4.25 | Q119: 1 | R119: 1 | S119: 0 | T119: 0
A120: A-42e5e1 | B120: Churn (3 concordam) | C120: DevTools | D120: ads | E120: TRUE | F120: TRUE | G120: TRUE | H120: 4936 | I120: 7 | J120: 1 | K120: 5.7495 | L120: 1 | M120: 411 | N120: 9.9757 | O120: 3 | P120: 4 | Q120: 1 | R120: 1 | S120: 1 | T120: 0
A121: A-7d514c | B121: Divergente | C121: HealthTech | D121: organic | E121: FALSE | F121: FALSE | G121: TRUE | H121: 15717 | I121: 9 | J121: 0.5556 | K121: 10.9076 | L121: 17 | M121: 502 | N121: 5.9761 | O121: 3 | P121: 5 | Q121: 1 | R121: 0 | S121: 0 | T121: 0
A122: A-65aeb5 | B122: Divergente | C122: DevTools | D122: partner | E122: FALSE | F122: TRUE | G122: TRUE | H122: 19893 | I122: 12 | J122: 0.6667 | K122: 11.2033 | L122: 9 | M122: 533 | N122: 7.5047 | O122: 2 | P122: 5 | Q122: 0 | R122: 1 | S122: 1 | T122: 1
A123: A-e2cd1b | B123: Ativa (3 concordam) | C123: DevTools | D123: other | E123: FALSE | F123: FALSE | G123: FALSE | H123: 12548 | I123: 9 | J123: 0.5556 | K123: 10.8747 | L123: 15 | M123: 465 | N123: 3.871 | O123: 5 | P123: 4 | Q123: 1 | R123: 0 | S123: 1 | T123: 0
A124: A-180abf | B124: Churn (3 concordam) | C124: DevTools | D124: event | E124: TRUE | F124: TRUE | G124: TRUE | H124: 24576 | I124: 9 | J124: 0.5556 | K124: 16.5914 | L124: 64 | M124: 499 | N124: 5.6112 | O124: 3 | P124: 3 | Q124: 1 | R124: 0 | S124: 1 | T124: 0
A125: A-f17767 | B125: Churn (3 concordam) | C125: DevTools | D125: event | E125: TRUE | F125: TRUE | G125: TRUE | H125: 14914 | I125: 14 | J125: 0.2143 | K125: 23.0308 | L125: 1 | M125: 713 | N125: 5.3296 | O125: 3 | P125: 4 | Q125: 1 | R125: 1 | S125: 1 | T125: 0
A126: A-5a184f | B126: Churn (3 concordam) | C126: DevTools | D126: other | E126: TRUE | F126: TRUE | G126: TRUE | H126: 19999 | I126: 10 | J126: 0.2 | K126: 18.4312 | L126: 1 | M126: 587 | N126: 4.9404 | O126: 3 | P126: 4.3333 | Q126: 0 | R126: 1 | S126: 1 | T126: 0
A127: A-7df7a7 | B127: Churn (3 concordam) | C127: DevTools | D127: organic | E127: TRUE | F127: TRUE | G127: TRUE | H127: 26568 | I127: 15 | J127: 0.2 | K127: 23.0965 | L127: 7 | M127: 922 | N127: 5.0976 | O127: 3 | P127: 4 | Q127: 0 | R127: 1 | S127: 1 | T127: 0
A128: A-1ac5e0 | B128: Divergente | C128: DevTools | D128: event | E128: TRUE | F128: FALSE | G128: FALSE | H128: 18249 | I128: 10 | J128: 1 | K128: 2.3655 | L128: 33 | M128: 558 | N128: 5.5556 | O128: 7 | P128: 3.8 | Q128: 0 | R128: 0 | S128: 1 | T128: 0
A129: A-52dd88 | B129: Ativa (3 concordam) | C129: Cybersecurity | D129: ads | E129: FALSE | F129: FALSE | G129: FALSE | H129: 16592 | I129: 11 | J129: 0.3636 | K129: 22.308 | L129: 23 | M129: 516 | N129: 6.3953 | O129: 1 | Q129: 1 | R129: 0 | S129: 0 | T129: 0
A130: A-bece89 | B130: Divergente | C130: Cybersecurity | D130: event | E130: FALSE | F130: TRUE | G130: FALSE | H130: 19250 | I130: 6 | J130: 0.1667 | K130: 13.0103 | L130: 26 | M130: 176 | N130: 7.3864 | O130: 4 | P130: 4 | Q130: 1 | R130: 0 | S130: 0 | T130: 0
A131: A-029f69 | B131: Divergente | C131: Cybersecurity | D131: event | E131: FALSE | F131: TRUE | G131: TRUE | H131: 13324 | I131: 16 | J131: 0.875 | K131: 9.8234 | L131: 3 | M131: 789 | N131: 5.3232 | O131: 2 | P131: 3 | Q131: 1 | R131: 0 | S131: 0 | T131: 0
A132: A-5c046d | B132: Ativa (3 concordam) | C132: EdTech | D132: partner | E132: FALSE | F132: FALSE | G132: FALSE | H132: 83886 | I132: 8 | J132: 1 | K132: 5.848 | L132: 93 | M132: 475 | N132: 4.8421 | O132: 1 | P132: 3 | Q132: 0 | R132: 0 | S132: 0 | T132: 1
...

Sheet Base_Tickets
A1: ticket_id | B1: account_id | C1: mes | D1: resolution_time_hours | E1: first_response_time_minutes | F1: satisfaction_score | G1: escalado | H1: priority
A2: T-0024de | B2: A-712f1c | C2: 45108 | D2: 27 | E2: 74 | G2: 0 | H2: high
A3: T-4d04b9 | B3: A-e43bf7 | C3: 45474 | D3: 27 | E3: 144 | G3: 0 | H3: urgent
A4: T-d5e12f | B4: A-0f3e88 | C4: 45566 | D4: 19 | E4: 93 | F4: 4 | G4: 0 | H4: urgent
A5: T-dfce9a | B5: A-4c56c9 | C5: 45536 | D5: 47 | E5: 126 | F5: 5 | G5: 0 | H5: medium
A6: T-c59f77 | B6: A-6f8ad2 | C6: 45597 | D6: 26 | E6: 8 | G6: 0 | H6: medium
A7: T-90f06d | B7: A-94c3cd | C7: 45108 | D7: 9 | E7: 60 | G7: 0 | H7: medium
A8: T-30b537 | B8: A-2e4581 | C8: 45170 | D8: 27 | E8: 64 | F8: 3 | G8: 0 | H8: urgent
A9: T-60242d | B9: A-72799b | C9: 45292 | D9: 12 | E9: 56 | F9: 4 | G9: 1 | H9: low
A10: T-7119c9 | B10: A-b179bf | C10: 45139 | D10: 16 | E10: 154 | G10: 0 | H10: urgent
A11: T-b0edf2 | B11: A-7cfe77 | C11: 45413 | D11: 28 | E11: 150 | F11: 3 | G11: 0 | H11: medium
A12: T-98a84a | B12: A-157070 | C12: 45261 | D12: 42 | E12: 26 | G12: 0 | H12: low
A13: T-04457d | B13: A-854864 | C13: 45474 | D13: 48 | E13: 140 | F13: 5 | G13: 0 | H13: medium
A14: T-6bd715 | B14: A-4e0e85 | C14: 45413 | D14: 50 | E14: 129 | G14: 0 | H14: medium
A15: T-13f1b8 | B15: A-5b4ebb | C15: 45261 | D15: 26 | E15: 121 | F15: 5 | G15: 0 | H15: low
A16: T-a3288b | B16: A-098560 | C16: 45627 | D16: 55 | E16: 26 | F16: 3 | G16: 0 | H16: low
A17: T-f8e2c3 | B17: A-40a557 | C17: 45352 | D17: 69 | E17: 60 | G17: 0 | H17: high
A18: T-4e7816 | B18: A-05f0e5 | C18: 45566 | D18: 36 | E18: 108 | G18: 0 | H18: low
A19: T-0dea8b | B19: A-671f31 | C19: 45292 | D19: 60 | E19: 45 | F19: 3 | G19: 0 | H19: medium
A20: T-ca96ba | B20: A-410e86 | C20: 45383 | D20: 3 | E20: 64 | G20: 0 | H20: high
A21: T-ac0b69 | B21: A-ac9111 | C21: 45352 | D21: 14 | E21: 86 | G21: 0 | H21: low
A22: T-0f1c67 | B22: A-78f02b | C22: 45566 | D22: 48 | E22: 51 | F22: 4 | G22: 0 | H22: low
A23: T-4fb3f2 | B23: A-c62e55 | C23: 44986 | D23: 59 | E23: 136 | F23: 3 | G23: 0 | H23: medium
A24: T-2b4423 | B24: A-158f4e | C24: 45261 | D24: 11 | E24: 99 | G24: 0 | H24: high
A25: T-b17401 | B25: A-50bb9f | C25: 45323 | D25: 12 | E25: 171 | F25: 3 | G25: 0 | H25: high
A26: T-462ece | B26: A-b9f5b1 | C26: 45108 | D26: 51 | E26: 50 | F26: 3 | G26: 1 | H26: low
A27: T-066714 | B27: A-b2225d | C27: 45383 | D27: 24 | E27: 52 | F27: 3 | G27: 0 | H27: high
A28: T-8c694d | B28: A-883b7d | C28: 45413 | D28: 15 | E28: 39 | F28: 3 | G28: 1 | H28: low
A29: T-804c6c | B29: A-751bd4 | C29: 45566 | D29: 28 | E29: 49 | F29: 4 | G29: 0 | H29: medium
A30: T-64b0b8 | B30: A-533452 | C30: 45170 | D30: 56 | E30: 16 | F30: 5 | G30: 0 | H30: low
A31: T-bfa749 | B31: A-684255 | C31: 45139 | D31: 1 | E31: 137 | F31: 5 | G31: 0 | H31: low
A32: T-3b24c1 | B32: A-0aaf6e | C32: 45444 | D32: 54 | E32: 151 | F32: 3 | G32: 0 | H32: high
A33: T-68c8a6 | B33: A-7c4956 | C33: 45536 | D33: 19 | E33: 34 | G33: 0 | H33: high
A34: T-bbe374 | B34: A-3ce5b8 | C34: 45292 | D34: 50 | E34: 155 | G34: 0 | H34: low
A35: T-bccf63 | B35: A-82d8a6 | C35: 45597 | D35: 70 | E35: 67 | F35: 3 | G35: 0 | H35: high
A36: T-98448a | B36: A-462d45 | C36: 45323 | D36: 18 | E36: 99 | F36: 4 | G36: 0 | H36: high
A37: T-f68dde | B37: A-118d55 | C37: 45536 | D37: 14 | E37: 1 | F37: 4 | G37: 0 | H37: medium
A38: T-5f84c5 | B38: A-1f559b | C38: 45292 | D38: 62 | E38: 28 | F38: 4 | G38: 0 | H38: high
A39: T-9bae5a | B39: A-7cfe77 | C39: 45383 | D39: 23 | E39: 176 | F39: 5 | G39: 0 | H39: urgent
A40: T-22842d | B40: A-533452 | C40: 45505 | D40: 8 | E40: 66 | F40: 3 | G40: 0 | H40: high
A41: T-f8b58d | B41: A-ee42db | C41: 44927 | D41: 57 | E41: 144 | G41: 0 | H41: urgent
A42: T-3a2a66 | B42: A-e98302 | C42: 45170 | D42: 66 | E42: 150 | G42: 0 | H42: low
A43: T-490c4a | B43: A-503d5a | C43: 45139 | D43: 9 | E43: 179 | G43: 0 | H43: urgent
A44: T-6cce32 | B44: A-659280 | C44: 45444 | D44: 6 | E44: 176 | F44: 4 | G44: 0 | H44: medium
A45: T-ec46f5 | B45: A-f5641b | C45: 45017 | D45: 55 | E45: 93 | G45: 0 | H45: high
A46: T-219077 | B46: A-fb186e | C46: 45323 | D46: 42 | E46: 58 | G46: 0 | H46: medium
A47: T-6b6fb7 | B47: A-716841 | C47: 45323 | D47: 4 | E47: 119 | F47: 3 | G47: 0 | H47: medium
A48: T-2e5ba4 | B48: A-0be015 | C48: 45627 | D48: 14 | E48: 46 | F48: 4 | G48: 1 | H48: low
A49: T-8001a4 | B49: A-c9bb3e | C49: 45047 | D49: 11 | E49: 53 | F49: 4 | G49: 1 | H49: urgent
A50: T-a1d9dd | B50: A-fd7ad3 | C50: 45383 | D50: 64 | E50: 21 | F50: 3 | G50: 0 | H50: urgent
A51: T-121d6f | B51: A-d5a319 | C51: 45536 | D51: 17 | E51: 132 | F51: 4 | G51: 1 | H51: low
A52: T-fd1ba2 | B52: A-d27f50 | C52: 45261 | D52: 40 | E52: 158 | F52: 4 | G52: 0 | H52: high
A53: T-b6d7ac | B53: A-a0ca4e | C53: 45200 | D53: 11 | E53: 12 | F53: 5 | G53: 1 | H53: low
A54: T-f2b9a5 | B54: A-f6b2fb | C54: 45292 | D54: 36 | E54: 138 | F54: 5 | G54: 1 | H54: medium
A55: T-61fc87 | B55: A-034368 | C55: 44927 | D55: 65 | E55: 127 | F55: 3 | G55: 0 | H55: medium
A56: T-00fa83 | B56: A-9208f0 | C56: 45017 | D56: 70 | E56: 6 | G56: 0 | H56: low
A57: T-358dd5 | B57: A-ced9aa | C57: 45139 | D57: 57 | E57: 131 | G57: 0 | H57: medium
A58: T-54e843 | B58: A-bb3bd4 | C58: 45566 | D58: 8 | E58: 63 | F58: 3 | G58: 0 | H58: medium
A59: T-50ad36 | B59: A-922109 | C59: 45047 | D59: 26 | E59: 126 | G59: 0 | H59: medium
A60: T-06bf16 | B60: A-4a4c2d | C60: 45139 | D60: 30 | E60: 44 | F60: 4 | G60: 0 | H60: medium
A61: T-f155f0 | B61: A-b179bf | C61: 45139 | D61: 6 | E61: 156 | G61: 0 | H61: high
A62: T-777753 | B62: A-ce66f8 | C62: 44927 | D62: 69 | E62: 74 | G62: 0 | H62: low
A63: T-857a8d | B63: A-bb3bd4 | C63: 45292 | D63: 66 | E63: 52 | G63: 0 | H63: medium
A64: T-384dcb | B64: A-bc4d48 | C64: 45597 | D64: 71 | E64: 6 | F64: 5 | G64: 1 | H64: urgent
A65: T-970c6c | B65: A-439b2f | C65: 45627 | D65: 20 | E65: 123 | G65: 0 | H65: urgent
A66: T-50c7f8 | B66: A-a1bbb6 | C66: 45292 | D66: 36 | E66: 47 | G66: 0 | H66: urgent
A67: T-a528f4 | B67: A-b78bf8 | C67: 45017 | D67: 24 | E67: 7 | F67: 3 | G67: 0 | H67: urgent
A68: T-7b7a5a | B68: A-1e50e0 | C68: 45566 | D68: 19 | E68: 170 | F68: 5 | G68: 1 | H68: high
A69: T-c9a73c | B69: A-b9f5b1 | C69: 45566 | D69: 18 | E69: 86 | F69: 4 | G69: 0 | H69: urgent
A70: T-486b6b | B70: A-883b7d | C70: 44927 | D70: 22 | E70: 102 | F70: 5 | G70: 0 | H70: urgent
A71: T-19cc99 | B71: A-c16b88 | C71: 45017 | D71: 53 | E71: 134 | G71: 0 | H71: high
A72: T-35fc90 | B72: A-e98302 | C72: 45200 | D72: 67 | E72: 121 | G72: 0 | H72: low
A73: T-d4142b | B73: A-700ade | C73: 45047 | D73: 66 | E73: 69 | F73: 4 | G73: 0 | H73: urgent
A74: T-6ba215 | B74: A-56962b | C74: 44986 | D74: 66 | E74: 73 | F74: 3 | G74: 0 | H74: low
A75: T-e5c785 | B75: A-b54c01 | C75: 44986 | D75: 26 | E75: 41 | F75: 3 | G75: 0 | H75: medium
A76: T-4f0d98 | B76: A-e40f45 | C76: 44986 | D76: 10 | E76: 19 | G76: 0 | H76: urgent
A77: T-e97da3 | B77: A-45ce7a | C77: 45383 | D77: 25 | E77: 81 | G77: 0 | H77: low
A78: T-990a0e | B78: A-fa3095 | C78: 45597 | D78: 48 | E78: 28 | G78: 0 | H78: high
A79: T-ce1dee | B79: A-d792a6 | C79: 45566 | D79: 32 | E79: 126 | G79: 0 | H79: low
A80: T-b7b797 | B80: A-bbc346 | C80: 45352 | D80: 35 | E80: 24 | G80: 0 | H80: medium
A81: T-847498 | B81: A-7cfe77 | C81: 45108 | D81: 59 | E81: 36 | G81: 0 | H81: high
A82: T-2ef49b | B82: A-cc1d8d | C82: 45170 | D82: 45 | E82: 33 | F82: 5 | G82: 0 | H82: medium
A83: T-fb6fa3 | B83: A-0a62f5 | C83: 45597 | D83: 8 | E83: 57 | G83: 0 | H83: urgent
A84: T-a3f900 | B84: A-ae052e | C84: 45108 | D84: 29 | E84: 126 | F84: 3 | G84: 0 | H84: medium
A85: T-b9e7df | B85: A-526d93 | C85: 45047 | D85: 5 | E85: 158 | G85: 0 | H85: medium
A86: T-0e6db2 | B86: A-ccc747 | C86: 45444 | D86: 60 | E86: 169 | F86: 5 | G86: 0 | H86: urgent
A87: T-4c2f4b | B87: A-726cfa | C87: 45261 | D87: 37 | E87: 150 | G87: 0 | H87: high
A88: T-e7dc15 | B88: A-39868b | C88: 45352 | D88: 22 | E88: 137 | G88: 0 | H88: medium
A89: T-9876fb | B89: A-2e3bad | C89: 45292 | D89: 14 | E89: 92 | G89: 0 | H89: high
A90: T-2c6679 | B90: A-0be015 | C90: 45474 | D90: 51 | E90: 73 | F90: 5 | G90: 0 | H90: medium
A91: T-03303d | B91: A-87aa7b | C91: 45231 | D91: 59 | E91: 7 | G91: 1 | H91: high
A92: T-1ed4c4 | B92: A-c62e55 | C92: 45352 | D92: 15 | E92: 129 | F92: 5 | G92: 0 | H92: urgent
A93: T-7c6ab3 | B93: A-65a46c | C93: 45627 | D93: 57 | E93: 96 | F93: 5 | G93: 0 | H93: urgent
A94: T-67bfcf | B94: A-3932db | C94: 45170 | D94: 36 | E94: 144 | F94: 3 | G94: 0 | H94: urgent
A95: T-088eb6 | B95: A-ac14bb | C95: 45352 | D95: 21 | E95: 23 | G95: 0 | H95: high
A96: T-b4bec0 | B96: A-117171 | C96: 45139 | D96: 33 | E96: 137 | G96: 0 | H96: urgent
A97: T-03d219 | B97: A-ae052e | C97: 45292 | D97: 53 | E97: 6 | G97: 0 | H97: urgent
A98: T-7c2d38 | B98: A-ad3abd | C98: 45597 | D98: 1 | E98: 35 | G98: 0 | H98: high
A99: T-1112c6 | B99: A-de24d5 | C99: 45170 | D99: 72 | E99: 24 | F99: 3 | G99: 0 | H99: urgent
A100: T-938c6d | B100: A-a8d89d | C100: 45139 | D100: 60 | E100: 132 | G100: 0 | H100: low
...

Sheet Base_Uso
A1: usage_id | B1: mes | C1: usage_count | D1: error_count
A2: U-1c6c24 | B2: 45108 | C2: 9 | D2: 0
A3: U-f07cb8 | B3: 45139 | C3: 9 | D3: 0
A4: U-096807 | B4: 45261 | C4: 9 | D4: 0
A5: U-6b1580 | B5: 45474 | C5: 5 | D5: 0
A6: U-720a29 | B6: 45627 | C6: 12 | D6: 0
A7: U-c5692d | B7: 45200 | C7: 11 | D7: 0
A8: U-7078db | B8: 45170 | C8: 8 | D8: 2
A9: U-a60033 | B9: 45078 | C9: 10 | D9: 0
A10: U-5cd930 | B10: 45323 | C10: 9 | D10: 1
A11: U-ebb375 | B11: 44958 | C11: 6 | D11: 0
A12: U-a7c89a | B12: 45505 | C12: 9 | D12: 0
A13: U-779058 | B13: 45231 | C13: 10 | D13: 0
... A25001: U-6c82cc | B25001: 45597 | C25001: 10 | D25001: 1
